{"2006": {"Groningen": {"Winschoten": 9600, "De Marne": 5440, "Eemsmond": 8180, "Menterwolde": 6240, "Stadskanaal": 17330, "Marum": 4920, "Hoogezand-Sappemeer": 17540, "Winsum": 7080, "Bedum": 5310, "Scheemda": 7050, "Haren": 10070, "Delfzijl": 13970, "Leek": 9550, "Grootegast": 5920, "Groningen": 91320, "Reiderland": 3490, "Pekela": 6650, "Bellingwedde": 4840, "Slochteren": 7300, "Vlagtwedde": 8380, "Ten Boer": 3570, "Loppersum": 5420, "Appingedam": 6290, "Veendam": 14250, "Zuidhorn": 9250}, "Gelderland": {"Berkelland": 22470, "Neerijnen": 5810, "Oude IJsselstreek": 20120, "Renkum": 16490, "Buren": 12790, "Elburg": 11150, "Scherpenzeel": 4490, "Westervoort": 7890, "West Maas en Waal": 9210, "Brummen": 10760, "Ubbergen": 4800, "Neder-Betuwe": 11250, "Lingewaard": 21980, "Putten": 11690, "Lingewaal": 5400, "Winterswijk": 14660, "Heerde": 9200, "Rheden": 22860, "Rozendaal": 770, "Overbetuwe": 21510, "Lochem": 16740, "Culemborg": 13680, "Wageningen": 17880, "Hattem": 6020, "Harderwijk": 20990, "Duiven": 13010, "Doesburg": 5860, "Barneveld": 25330, "Nijkerk": 19340, "Voorst": 11730, "Arnhem": 71950, "Heumen": 8510, "Oldebroek": 11320, "Groesbeek": 9680, "Groenlo": 14740, "Geldermalsen": 13240, "Apeldoorn": 79410, "Beuningen": 12500, "Doetinchem": 28610, "Zevenaar": 16110, "Epe": 16740, "Zaltbommel": 13130, "Druten": 9090, "Rijnwaarden": 5500, "Tiel": 20680, "Bronckhorst": 18970, "Ede": 54690, "Zutphen": 23910, "Millingen aan de Rijn": 2920, "Ermelo": 13380, "Nunspeet": 13500, "Maasdriel": 11700, "Nijmegen": 83250, "Montferland": 17600, "Aalten": 13740, "Wijchen": 19970}, "Flevoland": {"Noordoostpolder": 22690, "Urk": 8640, "Lelystad": 35960, "Almere": 89950, "Dronten": 18780, "Zeewolde": 9530}, "Noord-Holland": {"Langedijk": 13000, "Muiden": 3400, "Haarlemmerliede en Spaarnwoude": 2780, "Obdam": 3350, "Weesp": 8970, "Zeevang": 3120, "Hilversum": 43240, "Velsen": 34340, "Wijdemeren": 11960, "Medemblik": 4050, "Castricum": 17870, "Wester-Koggenland": 7040, "Hoorn": 34460, "Texel": 6920, "Naarden": 8930, "Zaanstad": 71100, "Wognum": 3960, "Aalsmeer": 12120, "Landsmeer": 5290, "Niedorp": 5800, "Drechterland": 9110, "Bloemendaal": 8990, "Anna Paulowna": 6940, "Ouder-Amstel": 6760, "Zandvoort": 8710, "Heerhugowaard": 24430, "Opmeer": 5590, "Heemstede": 13660, "Harenkarspel": 7720, "Heemskerk": 19120, "Waterland": 8640, "Bennebroek": 2720, "Wieringermeer": 6220, "Huizen": 21660, "Alkmaar": 48130, "Haarlemmermeer": 67760, "Schermer": 2390, "Heiloo": 11250, "Den Helder": 29760, "Andijk": 3150, "Schagen": 9460, "Oostzaan": 4720, "Amsterdam": 376950, "Noorder-Koggenland": 5260, "Uitgeest": 5950, "Edam-Volendam": 14160, "Diemen": 12230, "Bussum": 16600, "Purmerend": 39800, "Wormerland": 7920, "Beverwijk": 18630, "Zijpe": 5710, "Amstelveen": 41460, "Blaricum": 4720, "Graft-De Rijp": 3250, "Enkhuizen": 8920, "Laren": 5880, "Stede Broec": 10600, "Uithoorn": 13640, "Wieringen": 4330, "Beemster": 4230, "Haarlem": 75770, "Wervershoof": 4170}, "Friesland": {"Skarsterl\u00e2n": 13420, "Leeuwarderadeel": 5210, "W\u00fbnseradiel": 5840, "Ooststellingwerf": 13060, "Wymbritseradiel": 7950, "Ameland": 1720, "Harlingen": 7810, "Sneek": 16820, "Smallingerland": 27750, "Franekeradeel": 10330, "Weststellingwerf": 12740, "Terschelling": 2230, "Achtkarspelen": 13900, "Opsterland": 14760, "Dongeradeel": 12500, "Boarnsterhim": 9540, "Kollumerland en Nieuwkruisland": 6410, "Menaldumadeel": 6850, "het Bildt": 5390, "Bolsward": 4860, "Ferwerderadiel": 4370, "Gaasterl\u00e2n-Sleat": 5100, "Lemsterland": 6580, "Vlieland": 580, "Leeuwarden": 46970, "Tytsjerksteradiel": 16040, "Nijefurd": 5460, "Schiermonnikoog": 490, "Littenseradiel": 5350, "Heerenveen": 21810, "Dantumadeel": 9780}, "Zuid-Holland": {"Korendijk": 5430, "Capelle aan den IJssel": 33890, "Graafstroom": 4750, "Schoonhoven": 6200, "Alblasserdam": 9460, "Zoetermeer": 59680, "Pijnacker-Nootdorp": 20790, "Wassenaar": 13430, "Ouderkerk": 4080, "Waddinxveen": 13060, "Bleiswijk": 5030, "Jacobswoude": 5300, "Hendrik-Ido-Ambacht": 12430, "'s-Gravenhage": 241990, "Katwijk": 30610, "Gorinchem": 17420, "Middelharnis": 9050, "Westvoorne": 7210, "Binnenmaas": 9870, "Maassluis": 16230, "Nieuw-Lekkerland": 4630, "Alphen aan den Rijn": 35960, "Albrandswaard": 10550, "Barendrecht": 20750, "Hillegom": 10330, "Westland": 49180, "'s-Gravendeel": 4460, "Rotterdam": 300420, "Leiden": 60530, "Zederik": 6740, "Midden-Delfland": 8540, "Giessenlanden": 7180, "Nederlek": 7490, "Noordwijkerhout": 7500, "Voorschoten": 11880, "Bergambacht": 4770, "Ter Aar": 4420, "Cromstrijen": 6560, "Leidschendam-Voorburg": 38240, "Zoeterwoude": 4280, "Nieuwkoop": 5570, "Schiedam": 38350, "Nieuwerkerk aan den IJssel": 11130, "Oegstgeest": 11430, "Zwijndrecht": 22830, "Berkel en Rodenrijs": 9580, "Lisse": 11130, "Rijswijk": 25040, "Dordrecht": 60630, "Oostflakkee": 5090, "Papendrecht": 16000, "Bodegraven": 9660, "Liesveld": 4860, "Leerdam": 10550, "Boskoop": 7600, "Vlaardingen": 37220, "Leiderdorp": 13370, "Ridderkerk": 22930, "Delft": 45380, "Reeuwijk": 6380, "Brielle": 8080, "Noordwijk": 12320, "Moordrecht": 4030, "Alkemade": 7200, "Rozenburg": 6440, "Zevenhuizen-Moerkapelle": 5270, "Liemeer": 3260, "Oud-Beijerland": 12200, "Goedereede": 5860, "Sliedrecht": 12160, "Krimpen aan den IJssel": 14670, "Spijkenisse": 37980, "Teylingen": 17420, "Bergschenhoek": 8340, "Hellevoetsluis": 20110, "Strijen": 4620, "Bernisse": 6320, "Hardinxveld-Giessendam": 9000, "Rijnwoude": 9320, "Gouda": 36600, "Dirksland": 4180, "Vlist": 4900}, "Drenthe": {"Hoogeveen": 27260, "Emmen": 54940, "De Wolden": 11870, "Aa en Hunze": 12890, "Noordenveld": 15830, "Coevorden": 18140, "Assen": 32460, "Midden-Drenthe": 16740, "Meppel": 15700, "Borger-Odoorn": 13200, "Tynaarlo": 16260, "Westerveld": 9650}, "Overijssel": {"Almelo": 36420, "Dalfsen": 13020, "Ommen": 8600, "Twenterand": 16530, "Hof van Twente": 17650, "Tubbergen": 10160, "Staphorst": 7700, "Dinkelland": 12880, "Oldenzaal": 15640, "Hengelo": 41000, "Zwolle": 58200, "Wierden": 11690, "Losser": 11240, "Haaksbergen": 12100, "Hellendoorn": 18060, "Steenwijkerland": 21560, "Hardenberg": 28650, "Enschede": 75840, "Kampen": 24840, "Olst-Wijhe": 8570, "Deventer": 48930, "Zwartewaterland": 10850, "Borne": 10300, "Rijssen-Holten": 18380, "Raalte": 18600}, "Noord-Brabant": {"Nuenen, Gerwen en Nederwetten": 11390, "Bladel": 9400, "Landerd": 7210, "Geldrop-Mierlo": 19110, "Steenbergen": 11670, "Boekel": 4600, "Gemert-Bakel": 13810, "Gilze en Rijen": 12460, "Alphen-Chaam": 4690, "Geertruidenberg": 10390, "Boxmeer": 14550, "Deurne": 15770, "Bergen op Zoom": 33290, "Heusden": 21390, "Someren": 8910, "Maasdonk": 5630, "Waalre": 8420, "Boxtel": 14900, "Reusel-De Mierden": 6050, "Laarbeek": 10720, "Waalwijk": 23060, "Heeze-Leende": 7490, "Bernheze": 14670, "Goirle": 11140, "Bergeijk": 8900, "Etten-Leur": 20270, "Asten": 8010, "Dongen": 12750, "Veldhoven": 21760, "Oisterwijk": 13160, "Roosendaal": 39220, "Sint-Oedenrode": 8540, "Woensdrecht": 10540, "Zundert": 10190, "'s-Hertogenbosch": 68470, "Grave": 6310, "Rucphen": 11150, "Eindhoven": 103520, "Sint-Michielsgestel": 13970, "Breda": 87360, "Eersel": 8930, "Haaren": 6820, "Sint Anthonis": 5730, "Valkenswaard": 15690, "Moerdijk": 18330, "Veghel": 18330, "Cuijk": 12020, "Drimmelen": 13340, "Schijndel": 11480, "Tilburg": 101310, "Helmond": 42740, "Woudrichem": 7190, "Oosterhout": 26860, "Mill en Sint Hubert": 5450, "Halderberge": 14740, "Loon op Zand": 11460, "Werkendam": 13270, "Cranendonck": 9900, "Son en Breugel": 7720, "Oirschot": 8780, "Aalburg": 6080, "Uden": 20090, "Hilvarenbeek": 7400, "Baarle-Nassau": 3260, "Vught": 12840, "Oss": 38280, "Best": 14560, "Lith": 3300}, "Limburg": {"Simpelveld": 5710, "Kerkrade": 24910, "Voerendaal": 6500, "Helden": 9690, "Mook en Middelaar": 4030, "Beek": 8620, "Maasbracht": 6820, "Haelen": 5070, "Nederweert": 8110, "Sittard-Geleen": 49160, "Roerdalen": 5120, "Nuth": 8080, "Meijel": 2890, "Hunsel": 3080, "Horst aan de Maas": 14240, "Gulpen-Wittem": 7440, "Roermond": 23200, "Heerlen": 46510, "Meerssen": 10020, "Vaals": 5070, "Arcen en Velden": 4420, "Onderbanken": 4190, "Schinnen": 6690, "Roggel en Neer": 4060, "Thorn": 1310, "Valkenburg aan de Geul": 8700, "Kessel": 2080, "Beesel": 6740, "Ambt Montfort": 5530, "Margraten": 6660, "Meerlo-Wanssum": 3750, "Swalmen": 4440, "Venlo": 46440, "Heel": 4110, "Heythuysen": 6080, "Stein": 13370, "Eijsden": 5860, "Maasbree": 6320, "Sevenum": 3720, "Venray": 19300, "Weert": 24230, "Landgraaf": 19860, "Echt-Susteren": 16180, "Maastricht": 62290, "Brunssum": 15240, "Gennep": 8150}, "Utrecht": {"Vianen": 9940, "Leusden": 14670, "Woudenberg": 5600, "Eemnes": 4470, "Bunschoten": 9690, "Woerden": 24200, "Wijk bij Duurstede": 11830, "Lopik": 6830, "De Bilt": 22120, "Nieuwegein": 31110, "Rhenen": 9250, "Montfoort": 6750, "Baarn": 12780, "Abcoude": 4400, "De Ronde Venen": 17170, "Breukelen": 7390, "Zeist": 31400, "Houten": 22550, "Utrecht": 145440, "Oudewater": 5060, "Loenen": 4230, "Soest": 23180, "Utrechtse Heuvelrug": 25310, "Renswoude": 2180, "Veenendaal": 31410, "Bunnik": 7210, "Amersfoort": 70060, "Maarssen": 20140, "IJsselstein": 17370}, "Zeeland": {"Sluis": 12440, "Veere": 10880, "Tholen": 12450, "Hulst": 13970, "Kapelle": 5960, "Borsele": 11050, "Noord-Beveland": 3610, "Goes": 18880, "Schouwen-Duiveland": 17470, "Vlissingen": 22720, "Terneuzen": 27990, "Reimerswaal": 10500, "Middelburg": 24080}}, "2007": {"Groningen": {"Winschoten": 9580, "De Marne": 5320, "Eemsmond": 8210, "Menterwolde": 6210, "Stadskanaal": 17330, "Marum": 4880, "Hoogezand-Sappemeer": 17470, "Winsum": 7060, "Bedum": 5270, "Scheemda": 7050, "Haren": 9980, "Delfzijl": 13820, "Leek": 9660, "Grootegast": 5940, "Groningen": 91810, "Reiderland": 3480, "Pekela": 6590, "Bellingwedde": 4760, "Slochteren": 7400, "Vlagtwedde": 8350, "Ten Boer": 3600, "Loppersum": 5340, "Appingedam": 6260, "Veendam": 14230, "Zuidhorn": 9230}, "Gelderland": {"Berkelland": 22440, "Neerijnen": 5860, "Oude IJsselstreek": 20120, "Renkum": 16500, "Buren": 12820, "Elburg": 11230, "Scherpenzeel": 4480, "Westervoort": 7820, "West Maas en Waal": 9140, "Brummen": 10700, "Ubbergen": 4760, "Neder-Betuwe": 11240, "Lingewaard": 22320, "Putten": 11680, "Lingewaal": 5420, "Winterswijk": 14710, "Heerde": 9100, "Rheden": 22740, "Rozendaal": 780, "Overbetuwe": 21740, "Lochem": 16790, "Culemborg": 13710, "Wageningen": 18090, "Hattem": 5980, "Harderwijk": 21340, "Duiven": 13040, "Doesburg": 5880, "Barneveld": 25620, "Nijkerk": 19510, "Voorst": 11700, "Arnhem": 72020, "Heumen": 8390, "Oldebroek": 11250, "Groesbeek": 9710, "Geldermalsen": 13250, "Apeldoorn": 79170, "Beuningen": 12560, "Doetinchem": 28400, "Zevenaar": 16220, "Epe": 16760, "Zaltbommel": 13100, "Druten": 9130, "Rijnwaarden": 5480, "Tiel": 20740, "Bronckhorst": 19010, "Ede": 54860, "Oost Gelre": 14700, "Zutphen": 23880, "Millingen aan de Rijn": 2930, "Ermelo": 13390, "Nunspeet": 13510, "Maasdriel": 11680, "Nijmegen": 83940, "Montferland": 17520, "Aalten": 13780, "Wijchen": 19920}, "Flevoland": {"Noordoostpolder": 22660, "Urk": 8710, "Lelystad": 36330, "Almere": 91230, "Dronten": 18830, "Zeewolde": 9680}, "Noord-Holland": {"Langedijk": 12990, "Muiden": 3410, "Haarlemmerliede en Spaarnwoude": 2760, "Weesp": 9020, "Zeevang": 3130, "Hilversum": 43160, "Velsen": 34270, "Wijdemeren": 12040, "Medemblik": 13130, "Castricum": 17780, "Hoorn": 34650, "Texel": 6880, "Naarden": 8960, "Zaanstad": 71690, "Aalsmeer": 12550, "Landsmeer": 5290, "Niedorp": 5900, "Drechterland": 9140, "Bloemendaal": 9010, "Anna Paulowna": 6920, "Ouder-Amstel": 6680, "Zandvoort": 8660, "Heerhugowaard": 24620, "Opmeer": 5580, "Heemstede": 13640, "Harenkarspel": 7770, "Heemskerk": 19400, "Waterland": 8610, "Bennebroek": 2730, "Wieringermeer": 6290, "Huizen": 21560, "Alkmaar": 47950, "Haarlemmermeer": 69400, "Schermer": 2500, "Heiloo": 11160, "Koggenland": 10540, "Den Helder": 29420, "Andijk": 3160, "Schagen": 9640, "Oostzaan": 4740, "Bergen (NH.)": 16150, "Amsterdam": 377180, "Uitgeest": 6020, "Edam-Volendam": 14190, "Diemen": 12250, "Bussum": 16590, "Purmerend": 39860, "Wormerland": 7950, "Beverwijk": 18760, "Zijpe": 5720, "Amstelveen": 41430, "Blaricum": 4710, "Graft-De Rijp": 3260, "Enkhuizen": 8980, "Laren": 5860, "Stede Broec": 10570, "Uithoorn": 13680, "Wieringen": 4360, "Beemster": 4220, "Haarlem": 75700, "Wervershoof": 4180}, "Friesland": {"Skarsterl\u00e2n": 13440, "Leeuwarderadeel": 5160, "W\u00fbnseradiel": 5820, "Ooststellingwerf": 13150, "Wymbritseradiel": 7920, "Ameland": 1720, "Harlingen": 7740, "Sneek": 16840, "Smallingerland": 27780, "Franekeradeel": 10210, "Weststellingwerf": 12740, "Terschelling": 2210, "Achtkarspelen": 13890, "Opsterland": 14790, "Dongeradeel": 12420, "Boarnsterhim": 9620, "Kollumerland en Nieuwkruisland": 6430, "Menaldumadeel": 6820, "het Bildt": 5390, "Bolsward": 4940, "Ferwerderadiel": 4320, "Gaasterl\u00e2n-Sleat": 5070, "Lemsterland": 6590, "Vlieland": 590, "Leeuwarden": 47250, "Tytsjerksteradiel": 16120, "Nijefurd": 5470, "Schiermonnikoog": 470, "Littenseradiel": 5360, "Heerenveen": 21830, "Dantumadeel": 9730}, "Zuid-Holland": {"Korendijk": 5440, "Capelle aan den IJssel": 33750, "Graafstroom": 4760, "Schoonhoven": 6160, "Alblasserdam": 9550, "Zoetermeer": 60190, "Wassenaar": 13450, "Waddinxveen": 13010, "Jacobswoude": 5250, "Hendrik-Ido-Ambacht": 12640, "'s-Gravenhage": 241410, "Katwijk": 30710, "Gorinchem": 17420, "Middelharnis": 9110, "Westvoorne": 7160, "Binnenmaas": 14380, "Noordwijkerhout": 7600, "Nieuw-Lekkerland": 4610, "Alphen aan den Rijn": 36030, "Albrandswaard": 10740, "Barendrecht": 21700, "Hillegom": 10260, "Westland": 49480, "Oud-Beijerland": 12220, "Rotterdam": 298260, "Leiden": 60210, "Zederik": 6760, "Midden-Delfland": 8570, "Giessenlanden": 7150, "Nederlek": 7400, "Voorschoten": 11820, "Bergambacht": 4820, "Cromstrijen": 6530, "Leidschendam-Voorburg": 38070, "Zoeterwoude": 4240, "Nieuwkoop": 13320, "Schiedam": 38250, "Nieuwerkerk aan den IJssel": 11040, "Oegstgeest": 11480, "Zwijndrecht": 22770, "Maassluis": 16090, "Lisse": 11170, "Rijswijk": 24870, "Dordrecht": 60460, "Oostflakkee": 5060, "Papendrecht": 15970, "Bodegraven": 9680, "Liesveld": 4900, "Leerdam": 10510, "Boskoop": 7590, "Vlaardingen": 36740, "Leiderdorp": 13440, "Ridderkerk": 22880, "Zevenhuizen-Moerkapelle": 5290, "Delft": 45510, "Reeuwijk": 6320, "Brielle": 8010, "Noordwijk": 12300, "Moordrecht": 4030, "Alkemade": 7210, "Rozenburg": 6360, "Lansingerland": 23940, "Pijnacker-Nootdorp": 21330, "Ouderkerk": 4100, "Goedereede": 5880, "Sliedrecht": 12140, "Krimpen aan den IJssel": 14670, "Spijkenisse": 37660, "Teylingen": 17540, "Hellevoetsluis": 19970, "Strijen": 4570, "Bernisse": 6300, "Hardinxveld-Giessendam": 8950, "Rijnwoude": 9270, "Gouda": 36320, "Dirksland": 4180, "Vlist": 4890}, "Drenthe": {"Hoogeveen": 27380, "Emmen": 55020, "De Wolden": 11770, "Aa en Hunze": 12910, "Noordenveld": 15790, "Coevorden": 18100, "Assen": 32940, "Midden-Drenthe": 16850, "Meppel": 15990, "Borger-Odoorn": 13160, "Tynaarlo": 16190, "Westerveld": 9670}, "Overijssel": {"Almelo": 36370, "Dalfsen": 13060, "Ommen": 8630, "Twenterand": 16570, "Hof van Twente": 17740, "Tubbergen": 10240, "Staphorst": 7740, "Dinkelland": 12860, "Oldenzaal": 15760, "Hengelo": 41050, "Zwolle": 58960, "Wierden": 11640, "Losser": 11230, "Haaksbergen": 12110, "Hellendoorn": 18000, "Steenwijkerland": 21580, "Hardenberg": 28690, "Enschede": 75950, "Kampen": 24870, "Olst-Wijhe": 8610, "Deventer": 48990, "Zwartewaterland": 10860, "Borne": 10270, "Rijssen-Holten": 18440, "Raalte": 18620}, "Noord-Brabant": {"Nuenen, Gerwen en Nederwetten": 11320, "Bladel": 9360, "Landerd": 7210, "Geldrop-Mierlo": 19110, "Steenbergen": 11630, "Boekel": 4650, "Gemert-Bakel": 13760, "Gilze en Rijen": 12510, "Alphen-Chaam": 4670, "Geertruidenberg": 10360, "Boxmeer": 14430, "Deurne": 15800, "Bergen op Zoom": 33100, "Heusden": 21290, "Someren": 8900, "Maasdonk": 5630, "Waalre": 8400, "Boxtel": 15120, "Reusel-De Mierden": 6090, "Laarbeek": 10760, "Waalwijk": 22930, "Heeze-Leende": 7510, "Bernheze": 14700, "Goirle": 11100, "Bergeijk": 8920, "Etten-Leur": 20410, "Asten": 8000, "Dongen": 12750, "Veldhoven": 21640, "Oisterwijk": 13110, "Roosendaal": 39170, "Sint-Oedenrode": 8630, "Woensdrecht": 10710, "Zundert": 10240, "'s-Hertogenbosch": 68980, "Grave": 6300, "Rucphen": 11170, "Eindhoven": 103640, "Sint-Michielsgestel": 13940, "Breda": 87630, "Eersel": 8860, "Haaren": 6780, "Sint Anthonis": 5760, "Valkenswaard": 15670, "Moerdijk": 18350, "Veghel": 18310, "Cuijk": 12040, "Drimmelen": 13310, "Schijndel": 11470, "Tilburg": 101640, "Helmond": 42900, "Woudrichem": 7150, "Oosterhout": 27050, "Mill en Sint Hubert": 5420, "Halderberge": 14690, "Loon op Zand": 11530, "Werkendam": 13230, "Cranendonck": 10000, "Son en Breugel": 7720, "Oirschot": 8780, "Aalburg": 6140, "Uden": 20130, "Hilvarenbeek": 7440, "Baarle-Nassau": 3280, "Vught": 12800, "Oss": 38390, "Best": 14530, "Lith": 3310}, "Limburg": {"Simpelveld": 5700, "Kerkrade": 24620, "Voerendaal": 6460, "Helden": 9680, "Mook en Middelaar": 4040, "Beek": 8530, "Nederweert": 8160, "Sittard-Geleen": 49010, "Roerdalen": 10620, "Nuth": 8030, "Meijel": 2920, "Horst aan de Maas": 14300, "Gulpen-Wittem": 7390, "Roermond": 27580, "Heerlen": 46050, "Meerssen": 10010, "Vaals": 5010, "Arcen en Velden": 4400, "Onderbanken": 4200, "Schinnen": 6710, "Leudal": 18280, "Maasgouw": 12230, "Valkenburg aan de Geul": 8660, "Kessel": 2100, "Bergen (L.)": 6790, "Beesel": 6800, "Margraten": 6660, "Meerlo-Wanssum": 3750, "Venlo": 46470, "Stein": 13190, "Eijsden": 5820, "Maasbree": 6310, "Sevenum": 3760, "Venray": 19310, "Weert": 24200, "Landgraaf": 19730, "Echt-Susteren": 16200, "Maastricht": 61790, "Brunssum": 15210, "Gennep": 8240}, "Utrecht": {"Vianen": 9950, "Leusden": 14520, "Woudenberg": 5700, "Eemnes": 4470, "Bunschoten": 9700, "Woerden": 24290, "Wijk bij Duurstede": 11790, "Lopik": 6880, "De Bilt": 22090, "Nieuwegein": 30950, "Rhenen": 9400, "Montfoort": 6740, "Baarn": 12690, "Abcoude": 4390, "De Ronde Venen": 17310, "Breukelen": 7450, "Zeist": 31350, "Houten": 23060, "Utrecht": 149100, "Oudewater": 5060, "Loenen": 4180, "Soest": 23280, "Utrechtse Heuvelrug": 25220, "Renswoude": 2250, "Veenendaal": 31430, "Bunnik": 7170, "Amersfoort": 71040, "Maarssen": 20060, "IJsselstein": 17340}, "Zeeland": {"Sluis": 12410, "Veere": 10930, "Tholen": 12540, "Hulst": 14060, "Kapelle": 6070, "Borsele": 11020, "Noord-Beveland": 3640, "Goes": 18810, "Schouwen-Duiveland": 17310, "Vlissingen": 22710, "Terneuzen": 27840, "Reimerswaal": 10460, "Middelburg": 24220}}, "2004": {"Groningen": {"Winschoten": 9630, "De Marne": 5490, "Eemsmond": 8320, "Menterwolde": 6260, "Stadskanaal": 17070, "Marum": 5040, "Hoogezand-Sappemeer": 17280, "Winsum": 7190, "Bedum": 5400, "Scheemda": 7160, "Haren": 10100, "Delfzijl": 14380, "Leek": 9760, "Grootegast": 5830, "Groningen": 90560, "Reiderland": 3530, "Pekela": 6720, "Bellingwedde": 4860, "Slochteren": 7290, "Vlagtwedde": 8460, "Ten Boer": 3550, "Loppersum": 5480, "Appingedam": 6390, "Veendam": 14310, "Zuidhorn": 9120}, "Gelderland": {"Neerijnen": 5630, "Renkum": 16690, "Buren": 12820, "Elburg": 11000, "Scherpenzeel": 4560, "Westervoort": 8060, "West Maas en Waal": 9130, "Brummen": 10800, "Ubbergen": 4760, "Neder-Betuwe": 11190, "Lingewaard": 21600, "Putten": 11670, "Lingewaal": 5350, "Winterswijk": 14730, "Heerde": 9190, "Rheden": 23190, "Rozendaal": 760, "Overbetuwe": 20700, "Lochem": 9880, "Culemborg": 13420, "Wageningen": 17810, "Hattem": 6050, "Harderwijk": 20560, "Duiven": 13150, "Doesburg": 5790, "Barneveld": 25060, "Nijkerk": 18930, "Voorst": 11780, "Arnhem": 71690, "Heumen": 8450, "Oldebroek": 11360, "Groesbeek": 9680, "Groenlo": 4800, "Geldermalsen": 12940, "Apeldoorn": 79390, "Beuningen": 12700, "Doetinchem": 25010, "Zevenaar": 13270, "Epe": 16900, "Zaltbommel": 13130, "Druten": 8980, "Rijnwaarden": 5560, "Tiel": 20420, "Ede": 53780, "Zutphen": 18740, "Millingen aan de Rijn": 2960, "Ermelo": 13510, "Nunspeet": 13500, "Maasdriel": 11720, "Nijmegen": 81870, "Aalten": 9510, "Wijchen": 20060}, "Flevoland": {"Noordoostpolder": 22600, "Urk": 8420, "Lelystad": 35030, "Almere": 85710, "Dronten": 18620, "Zeewolde": 9380}, "Noord-Holland": {"Langedijk": 12640, "Muiden": 3390, "Haarlemmerliede en Spaarnwoude": 2810, "Obdam": 3370, "Weesp": 9120, "Zeevang": 3160, "Hilversum": 43100, "Velsen": 34300, "Wijdemeren": 11930, "Medemblik": 4010, "Castricum": 17930, "Wester-Koggenland": 6900, "Hoorn": 34420, "Texel": 6940, "Naarden": 8880, "Zaanstad": 70780, "Wognum": 3900, "Aalsmeer": 11520, "Landsmeer": 5320, "Niedorp": 5740, "Drechterland": 5140, "Bloemendaal": 8950, "Anna Paulowna": 6910, "Ouder-Amstel": 6740, "Zandvoort": 8790, "Heerhugowaard": 23360, "Opmeer": 5560, "Heemstede": 13680, "Harenkarspel": 7760, "Heemskerk": 18530, "Waterland": 8620, "Bennebroek": 2750, "Wieringermeer": 6210, "Huizen": 21570, "Alkmaar": 47950, "Haarlemmermeer": 63990, "Schermer": 2390, "Heiloo": 11240, "Den Helder": 30110, "Andijk": 3150, "Schagen": 9150, "Oostzaan": 4710, "Amsterdam": 374680, "Noorder-Koggenland": 5220, "Uitgeest": 5870, "Edam-Volendam": 14000, "Diemen": 12310, "Bussum": 16670, "Purmerend": 38780, "Wormerland": 7880, "Beverwijk": 18910, "Zijpe": 5590, "Amstelveen": 41410, "Blaricum": 4790, "Graft-De Rijp": 3220, "Enkhuizen": 8670, "Laren": 6120, "Stede Broec": 10600, "Uithoorn": 13560, "Wieringen": 4220, "Beemster": 4260, "Haarlem": 75720, "Wervershoof": 4140}, "Friesland": {"Skarsterl\u00e2n": 13440, "Leeuwarderadeel": 5280, "W\u00fbnseradiel": 5850, "Ooststellingwerf": 13290, "Wymbritseradiel": 8010, "Ameland": 1750, "Harlingen": 7880, "Sneek": 16750, "Smallingerland": 27390, "Franekeradeel": 10460, "Weststellingwerf": 12950, "Terschelling": 2220, "Achtkarspelen": 13900, "Opsterland": 14690, "Dongeradeel": 12450, "Boarnsterhim": 9440, "Kollumerland en Nieuwkruisland": 6430, "Menaldumadeel": 6930, "het Bildt": 5340, "Bolsward": 4760, "Ferwerderadiel": 4380, "Gaasterl\u00e2n-Sleat": 5060, "Lemsterland": 6530, "Vlieland": 580, "Leeuwarden": 46820, "Tytsjerksteradiel": 15910, "Nijefurd": 5480, "Schiermonnikoog": 500, "Littenseradiel": 5380, "Heerenveen": 21630, "Dantumadeel": 9940}, "Zuid-Holland": {"Korendijk": 5500, "Capelle aan den IJssel": 33740, "Graafstroom": 4760, "Schoonhoven": 6250, "Alblasserdam": 9420, "Zoetermeer": 58280, "Pijnacker-Nootdorp": 18720, "Wassenaar": 13370, "Ouderkerk": 4040, "Waddinxveen": 13160, "Bleiswijk": 5090, "Jacobswoude": 5240, "Hendrik-Ido-Ambacht": 11590, "'s-Gravenhage": 239520, "Katwijk": 21090, "Gorinchem": 17600, "Middelharnis": 8960, "Westvoorne": 7220, "Binnenmaas": 9690, "Maassluis": 16690, "Nieuw-Lekkerland": 4680, "Alphen aan den Rijn": 35680, "Albrandswaard": 9820, "Barendrecht": 18700, "Hillegom": 10460, "Westland": 48650, "'s-Gravendeel": 4440, "Rotterdam": 304670, "Leiden": 60800, "Zederik": 6770, "Midden-Delfland": 8360, "Giessenlanden": 7120, "Nederlek": 7550, "Noordwijkerhout": 7470, "Voorschoten": 11660, "Bergambacht": 4690, "Ter Aar": 4430, "Cromstrijen": 6540, "Leidschendam-Voorburg": 38570, "Zoeterwoude": 4300, "Nieuwkoop": 5550, "Schiedam": 38470, "Nieuwerkerk aan den IJssel": 11210, "Oegstgeest": 11090, "Zwijndrecht": 23210, "Berkel en Rodenrijs": 8740, "Lisse": 11210, "Rijswijk": 25320, "Dordrecht": 60910, "Oostflakkee": 5070, "Papendrecht": 15730, "Bodegraven": 9750, "Liesveld": 4850, "Leerdam": 10670, "Boskoop": 7560, "Vlaardingen": 38010, "Leiderdorp": 13420, "Ridderkerk": 23260, "Delft": 45720, "Reeuwijk": 6430, "Brielle": 8060, "Noordwijk": 12250, "Moordrecht": 4060, "Alkemade": 7160, "Rozenburg": 6600, "Zevenhuizen-Moerkapelle": 5200, "Liemeer": 3240, "Oud-Beijerland": 11890, "Goedereede": 5840, "Sliedrecht": 12160, "Krimpen aan den IJssel": 14780, "Spijkenisse": 38210, "Bergschenhoek": 7990, "Hellevoetsluis": 20130, "Strijen": 4650, "Bernisse": 6330, "Hardinxveld-Giessendam": 9010, "Rijnwoude": 9340, "Gouda": 36800, "Dirksland": 4150, "Vlist": 4880}, "Drenthe": {"Hoogeveen": 27070, "Emmen": 54770, "De Wolden": 11940, "Aa en Hunze": 12710, "Noordenveld": 16020, "Coevorden": 18100, "Assen": 31740, "Midden-Drenthe": 16470, "Meppel": 15700, "Borger-Odoorn": 13240, "Tynaarlo": 16400, "Westerveld": 9500}, "Overijssel": {"Almelo": 36500, "Dalfsen": 13020, "Ommen": 8420, "Twenterand": 16570, "Hof van Twente": 17570, "Tubbergen": 9960, "Staphorst": 7650, "Dinkelland": 12860, "Oldenzaal": 15680, "Hengelo": 40820, "Zwolle": 57050, "Wierden": 11630, "Losser": 11280, "Haaksbergen": 11990, "Hellendoorn": 18040, "Steenwijkerland": 21400, "Hardenberg": 28610, "Enschede": 74960, "Kampen": 24740, "Olst-Wijhe": 8470, "Deventer": 45320, "Zwartewaterland": 10910, "Borne": 10350, "Rijssen-Holten": 18220, "Raalte": 18540}, "Noord-Brabant": {"Nuenen, Gerwen en Nederwetten": 11640, "Bladel": 9430, "Landerd": 7230, "Geldrop-Mierlo": 19050, "Steenbergen": 11720, "Boekel": 4600, "Gemert-Bakel": 13720, "Gilze en Rijen": 12450, "Alphen-Chaam": 4660, "Geertruidenberg": 10420, "Boxmeer": 14730, "Deurne": 15890, "Bergen op Zoom": 33380, "Heusden": 21380, "Someren": 8990, "Maasdonk": 5690, "Waalre": 8410, "Boxtel": 14840, "Reusel-De Mierden": 6080, "Laarbeek": 10640, "Waalwijk": 23000, "Heeze-Leende": 7500, "Bernheze": 14260, "Goirle": 11360, "Bergeijk": 8920, "Etten-Leur": 19910, "Asten": 7910, "Dongen": 12570, "Veldhoven": 21150, "Oisterwijk": 13090, "Roosendaal": 39220, "Sint-Oedenrode": 8460, "Woensdrecht": 10670, "Zundert": 9990, "'s-Hertogenbosch": 67820, "Grave": 6270, "Rucphen": 11250, "Eindhoven": 103180, "Sint-Michielsgestel": 13870, "Breda": 85440, "Eersel": 8950, "Haaren": 6910, "Sint Anthonis": 5790, "Valkenswaard": 15720, "Moerdijk": 18380, "Veghel": 18390, "Cuijk": 11980, "Drimmelen": 13330, "Schijndel": 11660, "Tilburg": 100530, "Helmond": 42420, "Woudrichem": 7160, "Oosterhout": 26960, "Mill en Sint Hubert": 5450, "Halderberge": 14870, "Loon op Zand": 11590, "Werkendam": 13180, "Cranendonck": 9910, "Son en Breugel": 7560, "Oirschot": 8810, "Aalburg": 6050, "Uden": 19970, "Hilvarenbeek": 7380, "Baarle-Nassau": 3210, "Vught": 12790, "Oss": 38260, "Best": 14330, "Lith": 3300}, "Limburg": {"Simpelveld": 5770, "Kerkrade": 25230, "Voerendaal": 6470, "Helden": 9640, "Mook en Middelaar": 4000, "Beek": 8690, "Maasbracht": 6850, "Haelen": 5100, "Nederweert": 7930, "Sittard-Geleen": 49490, "Roerdalen": 5150, "Nuth": 8110, "Meijel": 2890, "Hunsel": 3060, "Horst aan de Maas": 14270, "Gulpen-Wittem": 7540, "Roermond": 22950, "Heerlen": 47660, "Meerssen": 10140, "Vaals": 5220, "Arcen en Velden": 4400, "Onderbanken": 4220, "Schinnen": 6770, "Roggel en Neer": 4040, "Thorn": 1270, "Valkenburg aan de Geul": 8920, "Kessel": 2050, "Beesel": 6640, "Ambt Montfort": 5510, "Margraten": 6660, "Meerlo-Wanssum": 3740, "Swalmen": 4420, "Venlo": 46380, "Heel": 4150, "Heythuysen": 6030, "Stein": 13340, "Eijsden": 5910, "Maasbree": 6320, "Sevenum": 3630, "Venray": 19280, "Weert": 24300, "Landgraaf": 20160, "Echt-Susteren": 16130, "Maastricht": 63260, "Brunssum": 15160, "Gennep": 8180}, "Utrecht": {"Vianen": 9980, "Leusden": 14770, "Woudenberg": 5600, "Eemnes": 4370, "Bunschoten": 9670, "Woerden": 24280, "Wijk bij Duurstede": 11860, "Lopik": 6820, "De Bilt": 22270, "Nieuwegein": 31160, "Rhenen": 9030, "Montfoort": 6690, "Baarn": 12760, "Abcoude": 4400, "De Ronde Venen": 17170, "Breukelen": 7340, "Zeist": 31470, "Houten": 21480, "Utrecht": 139940, "Oudewater": 4960, "Loenen": 4230, "Soest": 23000, "Renswoude": 2140, "Veenendaal": 31080, "Bunnik": 7100, "Amersfoort": 67890, "Maarssen": 20290, "IJsselstein": 17110}, "Zeeland": {"Sluis": 12500, "Veere": 10980, "Tholen": 12180, "Hulst": 13940, "Kapelle": 5890, "Borsele": 11010, "Noord-Beveland": 3550, "Goes": 18850, "Schouwen-Duiveland": 17380, "Vlissingen": 22780, "Terneuzen": 27950, "Reimerswaal": 10390, "Middelburg": 23720}}, "2005": {"Groningen": {"Winschoten": 9600, "De Marne": 5530, "Eemsmond": 8220, "Menterwolde": 6220, "Stadskanaal": 17150, "Marum": 4930, "Hoogezand-Sappemeer": 17460, "Winsum": 7190, "Bedum": 5340, "Scheemda": 7080, "Haren": 10120, "Delfzijl": 14170, "Leek": 9740, "Grootegast": 5890, "Groningen": 91300, "Reiderland": 3490, "Pekela": 6700, "Bellingwedde": 4830, "Slochteren": 7310, "Vlagtwedde": 8320, "Ten Boer": 3580, "Loppersum": 5480, "Appingedam": 6380, "Veendam": 14300, "Zuidhorn": 9190}, "Gelderland": {"Berkelland": 22390, "Neerijnen": 5750, "Oude IJsselstreek": 20210, "Renkum": 16660, "Buren": 12800, "Elburg": 11140, "Scherpenzeel": 4530, "Westervoort": 8010, "West Maas en Waal": 9170, "Brummen": 10750, "Ubbergen": 4800, "Neder-Betuwe": 11220, "Lingewaard": 21670, "Putten": 11660, "Lingewaal": 5360, "Winterswijk": 14730, "Heerde": 9170, "Rheden": 23140, "Rozendaal": 760, "Overbetuwe": 21250, "Lochem": 16740, "Culemborg": 13660, "Wageningen": 17840, "Hattem": 6040, "Harderwijk": 20720, "Duiven": 13080, "Doesburg": 5760, "Barneveld": 25100, "Nijkerk": 19180, "Voorst": 11770, "Arnhem": 71520, "Heumen": 8490, "Oldebroek": 11400, "Groesbeek": 9650, "Groenlo": 14870, "Geldermalsen": 13190, "Apeldoorn": 79470, "Beuningen": 12630, "Doetinchem": 28580, "Zevenaar": 16020, "Epe": 16780, "Zaltbommel": 13130, "Druten": 9040, "Rijnwaarden": 5510, "Tiel": 20420, "Bronckhorst": 18910, "Ede": 54380, "Zutphen": 23660, "Millingen aan de Rijn": 2950, "Ermelo": 13440, "Nunspeet": 13540, "Maasdriel": 11720, "Nijmegen": 82550, "Montferland": 17640, "Aalten": 13740, "Wijchen": 20130}, "Flevoland": {"Noordoostpolder": 22630, "Urk": 8540, "Lelystad": 35580, "Almere": 88050, "Dronten": 18710, "Zeewolde": 9410}, "Noord-Holland": {"Langedijk": 13000, "Muiden": 3400, "Haarlemmerliede en Spaarnwoude": 2800, "Obdam": 3360, "Weesp": 9040, "Zeevang": 3120, "Hilversum": 43220, "Velsen": 34240, "Wijdemeren": 11910, "Medemblik": 4000, "Castricum": 17880, "Wester-Koggenland": 6980, "Hoorn": 34610, "Texel": 6940, "Naarden": 8940, "Zaanstad": 70880, "Wognum": 3910, "Aalsmeer": 11720, "Landsmeer": 5280, "Niedorp": 5800, "Drechterland": 5230, "Bloemendaal": 9010, "Anna Paulowna": 6900, "Ouder-Amstel": 6800, "Zandvoort": 8740, "Heerhugowaard": 23880, "Opmeer": 5570, "Heemstede": 13650, "Harenkarspel": 7740, "Heemskerk": 18610, "Waterland": 8670, "Bennebroek": 2720, "Wieringermeer": 6150, "Huizen": 21670, "Alkmaar": 48050, "Haarlemmermeer": 66060, "Schermer": 2370, "Heiloo": 11240, "Den Helder": 29970, "Andijk": 3160, "Schagen": 9350, "Oostzaan": 4720, "Amsterdam": 376630, "Noorder-Koggenland": 5250, "Uitgeest": 5900, "Edam-Volendam": 14100, "Diemen": 12250, "Bussum": 16580, "Purmerend": 39340, "Wormerland": 7920, "Beverwijk": 18820, "Zijpe": 5650, "Amstelveen": 41510, "Blaricum": 4760, "Graft-De Rijp": 3240, "Enkhuizen": 8680, "Laren": 6100, "Stede Broec": 10650, "Uithoorn": 13720, "Wieringen": 4280, "Beemster": 4250, "Haarlem": 75500, "Wervershoof": 4180}, "Friesland": {"Skarsterl\u00e2n": 13430, "Leeuwarderadeel": 5250, "W\u00fbnseradiel": 5820, "Ooststellingwerf": 13200, "Wymbritseradiel": 8030, "Ameland": 1750, "Harlingen": 7950, "Sneek": 16760, "Smallingerland": 27540, "Franekeradeel": 10370, "Weststellingwerf": 12910, "Terschelling": 2230, "Achtkarspelen": 13870, "Opsterland": 14720, "Dongeradeel": 12500, "Boarnsterhim": 9520, "Kollumerland en Nieuwkruisland": 6410, "Menaldumadeel": 6910, "het Bildt": 5370, "Bolsward": 4800, "Ferwerderadiel": 4370, "Gaasterl\u00e2n-Sleat": 5060, "Lemsterland": 6560, "Vlieland": 580, "Leeuwarden": 46900, "Tytsjerksteradiel": 15960, "Nijefurd": 5500, "Schiermonnikoog": 500, "Littenseradiel": 5360, "Heerenveen": 21770, "Dantumadeel": 9850}, "Zuid-Holland": {"Korendijk": 5480, "Capelle aan den IJssel": 33800, "Graafstroom": 4750, "Schoonhoven": 6220, "Alblasserdam": 9430, "Zoetermeer": 59110, "Pijnacker-Nootdorp": 19840, "Wassenaar": 13380, "Ouderkerk": 4050, "Waddinxveen": 13140, "Bleiswijk": 5050, "Jacobswoude": 5270, "Hendrik-Ido-Ambacht": 11990, "'s-Gravenhage": 240620, "Katwijk": 21180, "Gorinchem": 17480, "Middelharnis": 8930, "Westvoorne": 7220, "Binnenmaas": 9790, "Maassluis": 16520, "Nieuw-Lekkerland": 4710, "Alphen aan den Rijn": 35750, "Albrandswaard": 10310, "Barendrecht": 19750, "Hillegom": 10400, "Westland": 48960, "'s-Gravendeel": 4450, "Rotterdam": 303620, "Leiden": 60780, "Zederik": 6760, "Midden-Delfland": 8350, "Giessenlanden": 7140, "Nederlek": 7520, "Noordwijkerhout": 7500, "Voorschoten": 11780, "Bergambacht": 4690, "Ter Aar": 4420, "Cromstrijen": 6550, "Leidschendam-Voorburg": 38580, "Zoeterwoude": 4290, "Nieuwkoop": 5580, "Schiedam": 38450, "Nieuwerkerk aan den IJssel": 11150, "Oegstgeest": 11120, "Zwijndrecht": 23130, "Berkel en Rodenrijs": 9020, "Lisse": 11160, "Rijswijk": 25170, "Dordrecht": 60780, "Oostflakkee": 5050, "Papendrecht": 15860, "Bodegraven": 9700, "Liesveld": 4860, "Leerdam": 10630, "Boskoop": 7600, "Vlaardingen": 37660, "Leiderdorp": 13420, "Ridderkerk": 23060, "Delft": 45380, "Reeuwijk": 6420, "Brielle": 8080, "Noordwijk": 12300, "Moordrecht": 4030, "Alkemade": 7180, "Rozenburg": 6580, "Zevenhuizen-Moerkapelle": 5240, "Liemeer": 3250, "Oud-Beijerland": 12110, "Goedereede": 5860, "Sliedrecht": 12190, "Krimpen aan den IJssel": 14750, "Spijkenisse": 38050, "Bergschenhoek": 8120, "Hellevoetsluis": 20130, "Strijen": 4640, "Bernisse": 6310, "Hardinxveld-Giessendam": 9010, "Rijnwoude": 9340, "Gouda": 36790, "Dirksland": 4190, "Vlist": 4880}, "Drenthe": {"Hoogeveen": 27160, "Emmen": 54930, "De Wolden": 11920, "Aa en Hunze": 12770, "Noordenveld": 15860, "Coevorden": 18100, "Assen": 32110, "Midden-Drenthe": 16580, "Meppel": 15600, "Borger-Odoorn": 13220, "Tynaarlo": 16420, "Westerveld": 9560}, "Overijssel": {"Almelo": 36550, "Dalfsen": 13040, "Ommen": 8460, "Twenterand": 16580, "Hof van Twente": 17560, "Tubbergen": 10090, "Staphorst": 7670, "Dinkelland": 12870, "Oldenzaal": 15660, "Hengelo": 40930, "Zwolle": 57620, "Wierden": 11700, "Losser": 11260, "Haaksbergen": 12050, "Hellendoorn": 18120, "Steenwijkerland": 21450, "Hardenberg": 28630, "Enschede": 75340, "Kampen": 24740, "Olst-Wijhe": 8500, "Deventer": 48510, "Zwartewaterland": 10820, "Borne": 10340, "Rijssen-Holten": 18340, "Raalte": 18570}, "Noord-Brabant": {"Nuenen, Gerwen en Nederwetten": 11540, "Bladel": 9410, "Landerd": 7250, "Geldrop-Mierlo": 19150, "Steenbergen": 11710, "Boekel": 4620, "Gemert-Bakel": 13760, "Gilze en Rijen": 12470, "Alphen-Chaam": 4710, "Geertruidenberg": 10400, "Boxmeer": 14650, "Deurne": 15840, "Bergen op Zoom": 33460, "Heusden": 21360, "Someren": 8900, "Maasdonk": 5670, "Waalre": 8420, "Boxtel": 14860, "Reusel-De Mierden": 6050, "Laarbeek": 10650, "Waalwijk": 23030, "Heeze-Leende": 7510, "Bernheze": 14470, "Goirle": 11240, "Bergeijk": 8910, "Etten-Leur": 20010, "Asten": 8000, "Dongen": 12710, "Veldhoven": 21300, "Oisterwijk": 13130, "Roosendaal": 39270, "Sint-Oedenrode": 8460, "Woensdrecht": 10580, "Zundert": 10060, "'s-Hertogenbosch": 68090, "Grave": 6300, "Rucphen": 11200, "Eindhoven": 103440, "Sint-Michielsgestel": 13860, "Breda": 86440, "Eersel": 8980, "Haaren": 6860, "Sint Anthonis": 5720, "Valkenswaard": 15740, "Moerdijk": 18380, "Veghel": 18400, "Cuijk": 11990, "Drimmelen": 13330, "Schijndel": 11510, "Tilburg": 100740, "Helmond": 42830, "Woudrichem": 7210, "Oosterhout": 26910, "Mill en Sint Hubert": 5450, "Halderberge": 14780, "Loon op Zand": 11540, "Werkendam": 13240, "Cranendonck": 9850, "Son en Breugel": 7610, "Oirschot": 8830, "Aalburg": 6040, "Uden": 20040, "Hilvarenbeek": 7400, "Baarle-Nassau": 3230, "Vught": 12850, "Oss": 38260, "Best": 14490, "Lith": 3300}, "Limburg": {"Simpelveld": 5750, "Kerkrade": 24990, "Voerendaal": 6450, "Helden": 9680, "Mook en Middelaar": 4040, "Beek": 8660, "Maasbracht": 6820, "Haelen": 5040, "Nederweert": 8030, "Sittard-Geleen": 49310, "Roerdalen": 5140, "Nuth": 8090, "Meijel": 2900, "Hunsel": 3080, "Horst aan de Maas": 14230, "Gulpen-Wittem": 7490, "Roermond": 23080, "Heerlen": 47120, "Meerssen": 10050, "Vaals": 5140, "Arcen en Velden": 4430, "Onderbanken": 4220, "Schinnen": 6720, "Roggel en Neer": 4090, "Thorn": 1320, "Valkenburg aan de Geul": 8810, "Kessel": 2070, "Beesel": 6660, "Ambt Montfort": 5480, "Margraten": 6660, "Meerlo-Wanssum": 3770, "Swalmen": 4450, "Venlo": 46500, "Heel": 4140, "Heythuysen": 6070, "Stein": 13430, "Eijsden": 5860, "Maasbree": 6320, "Sevenum": 3670, "Venray": 19360, "Weert": 24300, "Landgraaf": 20050, "Echt-Susteren": 16200, "Maastricht": 62870, "Brunssum": 15280, "Gennep": 8190}, "Utrecht": {"Vianen": 9990, "Leusden": 14670, "Woudenberg": 5610, "Eemnes": 4450, "Bunschoten": 9710, "Woerden": 24280, "Wijk bij Duurstede": 11870, "Lopik": 6860, "De Bilt": 22180, "Nieuwegein": 31050, "Rhenen": 9030, "Montfoort": 6710, "Baarn": 12720, "Abcoude": 4380, "De Ronde Venen": 17180, "Breukelen": 7340, "Zeist": 31430, "Houten": 22080, "Utrecht": 142690, "Oudewater": 5060, "Loenen": 4230, "Soest": 23100, "Renswoude": 2160, "Veenendaal": 31220, "Bunnik": 7150, "Amersfoort": 68880, "Maarssen": 20260, "IJsselstein": 17150}, "Zeeland": {"Sluis": 12530, "Veere": 10960, "Tholen": 12330, "Hulst": 13970, "Kapelle": 5910, "Borsele": 11060, "Noord-Beveland": 3590, "Goes": 18930, "Schouwen-Duiveland": 17460, "Vlissingen": 22870, "Terneuzen": 27950, "Reimerswaal": 10440, "Middelburg": 23820}}, "2014": {"Groningen": {"Oldambt": 19510, "Stadskanaal": 16615, "Eemsmond": 7785, "Menterwolde": 6035, "De Marne": 5025, "Marum": 5065, "Hoogezand-Sappemeer": 17350, "Winsum": 6975, "Bedum": 5245, "Haren": 9855, "Delfzijl": 12835, "Leek": 9905, "Grootegast": 5950, "Groningen": 99890, "Pekela": 6315, "Bellingwedde": 4470, "Slochteren": 7635, "Vlagtwedde": 7995, "Ten Boer": 3750, "Loppersum": 5040, "Appingedam": 6215, "Veendam": 14020, "Zuidhorn": 9395}, "Gelderland": {"Berkelland": 22195, "Neerijnen": 5955, "Oude IJsselstreek": 19765, "Renkum": 16280, "Buren": 13030, "Elburg": 11435, "Scherpenzeel": 4810, "Westervoort": 7685, "West Maas en Waal": 9275, "Brummen": 10700, "Ubbergen": 4755, "Neder-Betuwe": 11285, "Lingewaard": 23045, "Putten": 12020, "Lingewaal": 5560, "Winterswijk": 14485, "Heerde": 9395, "Rheden": 22335, "Rozendaal": 760, "Overbetuwe": 23485, "Lochem": 16925, "Culemborg": 13905, "Wageningen": 19410, "Hattem": 5975, "Harderwijk": 23230, "Duiven": 13010, "Doesburg": 5835, "Barneveld": 27195, "Nijkerk": 20405, "Voorst": 11890, "Arnhem": 75795, "Heumen": 8210, "Oldebroek": 11340, "Groesbeek": 9630, "Geldermalsen": 13285, "Apeldoorn": 79750, "Beuningen": 12655, "Doetinchem": 28505, "Zevenaar": 16455, "Epe": 16365, "Zaltbommel": 13550, "Druten": 9175, "Rijnwaarden": 5490, "Tiel": 21005, "Bronckhorst": 18560, "Ede": 56355, "Oost Gelre": 14595, "Zutphen": 24125, "Millingen aan de Rijn": 2935, "Ermelo": 13160, "Nunspeet": 13520, "Maasdriel": 11945, "Nijmegen": 87610, "Montferland": 17490, "Aalten": 13510, "Wijchen": 20740}, "Flevoland": {"Noordoostpolder": 22890, "Urk": 9630, "Lelystad": 38140, "Almere": 98775, "Dronten": 19950, "Zeewolde": 10555}, "Noord-Holland": {"Langedijk": 13490, "Muiden": 3230, "Haarlemmerliede en Spaarnwoude": 2815, "Zeevang": 3170, "Hilversum": 44255, "Velsen": 33880, "Wijdemeren": 11840, "Medemblik": 21290, "Castricum": 17490, "Hoorn": 36390, "Texel": 6825, "Naarden": 8920, "Zaanstad": 76140, "Aalsmeer": 15535, "Landsmeer": 5440, "Drechterland": 9510, "Bloemendaal": 11570, "Ouder-Amstel": 6820, "Zandvoort": 8605, "Heerhugowaard": 26470, "Opmeer": 5620, "Heemstede": 14005, "Heemskerk": 19935, "Waterland": 8640, "Weesp": 9400, "Huizen": 21195, "Alkmaar": 48115, "Haarlemmermeer": 72360, "Schermer": 2710, "Heiloo": 11525, "Koggenland": 11190, "Den Helder": 28605, "Schagen": 22945, "Oostzaan": 4670, "Bergen (NH.)": 15520, "Amsterdam": 411510, "Uitgeest": 6610, "Edam-Volendam": 14470, "Diemen": 13315, "Bussum": 17050, "Purmerend": 40695, "Wormerland": 7915, "Beverwijk": 20240, "Amstelveen": 44555, "Blaricum": 4700, "Graft-De Rijp": 3210, "Enkhuizen": 9135, "Laren": 5775, "Stede Broec": 10665, "Uithoorn": 14400, "Hollands Kroon": 23470, "Beemster": 4455, "Haarlem": 79365}, "Friesland": {"De Friese Meren": 25520, "Leeuwarderadeel": 5140, "Ooststellingwerf": 12810, "Ameland": 1820, "Harlingen": 7885, "Smallingerland": 27870, "Franekeradeel": 10175, "Weststellingwerf": 12675, "Dantumadiel": 9490, "Achtkarspelen": 13760, "Opsterland": 14950, "Dongeradeel": 12075, "Kollumerland en Nieuwkruisland": 6260, "het Bildt": 5190, "Ferwerderadiel": 4320, "Terschelling": 2245, "Menameradiel": 6685, "Vlieland": 565, "Leeuwarden": 54390, "Tytsjerksteradiel": 16025, "Schiermonnikoog": 465, "Littenseradiel": 5350, "S\u00fadwest-Frysl\u00e2n": 42105, "Heerenveen": 25285}, "Zuid-Holland": {"Korendijk": 5350, "Kaag en Braassem": 12695, "Capelle aan den IJssel": 34205, "Schoonhoven": 6035, "Alblasserdam": 10105, "Zoetermeer": 63160, "Wassenaar": 13530, "Waddinxveen": 12805, "Hendrik-Ido-Ambacht": 14705, "'s-Gravenhage": 257630, "Katwijk": 31565, "Gorinchem": 17860, "Binnenmaas": 14495, "Noordwijkerhout": 7940, "Alphen aan den Rijn": 53805, "Barendrecht": 24045, "Hillegom": 10555, "Westland": 51830, "Oud-Beijerland": 12120, "Rotterdam": 314005, "Leiden": 62275, "Zederik": 6825, "Midden-Delfland": 9120, "Giessenlanden": 7100, "Bodegraven-Reeuwijk": 16500, "Nederlek": 7135, "Voorschoten": 12910, "Bergambacht": 5035, "Cromstrijen": 6405, "Zoeterwoude": 4060, "Nieuwkoop": 13335, "Schiedam": 38840, "Lansingerland": 28750, "Maassluis": 16370, "Pijnacker-Nootdorp": 25620, "Dordrecht": 60135, "Albrandswaard": 12615, "Papendrecht": 16325, "Leerdam": 10490, "Lisse": 11330, "Zuidplas": 20620, "Vlaardingen": 36380, "Leiderdorp": 13875, "Ridderkerk": 23385, "Delft": 46650, "Westvoorne": 7060, "Brielle": 8320, "Noordwijk": 12805, "Zwijndrecht": 22905, "Oegstgeest": 11890, "Rijswijk": 25080, "Goeree-Overflakkee": 24390, "Leidschendam-Voorburg": 38265, "Teylingen": 17925, "Sliedrecht": 12470, "Krimpen aan den IJssel": 14815, "Spijkenisse": 37035, "Hellevoetsluis": 19605, "Strijen": 4340, "Bernisse": 6200, "Hardinxveld-Giessendam": 8920, "Molenwaard": 14285, "Gouda": 36205, "Ouderkerk": 4150, "Vlist": 4855}, "Drenthe": {"Hoogeveen": 27490, "Emmen": 54580, "De Wolden": 11785, "Aa en Hunze": 12755, "Noordenveld": 15625, "Coevorden": 18010, "Assen": 34200, "Midden-Drenthe": 16715, "Meppel": 16790, "Borger-Odoorn": 12830, "Tynaarlo": 16485, "Westerveld": 9490}, "Overijssel": {"Almelo": 36450, "Dalfsen": 13655, "Ommen": 8625, "Twenterand": 16735, "Hof van Twente": 17615, "Tubbergen": 10400, "Staphorst": 7990, "Dinkelland": 12700, "Oldenzaal": 16100, "Hengelo": 40580, "Zwolle": 62770, "Wierden": 11950, "Losser": 11265, "Haaksbergen": 12095, "Hellendoorn": 17850, "Steenwijkerland": 21690, "Hardenberg": 29440, "Enschede": 78160, "Kampen": 25725, "Olst-Wijhe": 8785, "Deventer": 49865, "Zwartewaterland": 10925, "Borne": 10985, "Rijssen-Holten": 18935, "Raalte": 18175}, "Noord-Brabant": {"Nuenen, Gerwen en Nederwetten": 11385, "Bladel": 9780, "Landerd": 7495, "Geldrop-Mierlo": 19555, "Steenbergen": 11635, "Boekel": 4925, "Gemert-Bakel": 14500, "Gilze en Rijen": 13000, "Alphen-Chaam": 4795, "Geertruidenberg": 10855, "Boxmeer": 14075, "Deurne": 15765, "Bergen op Zoom": 33535, "Heusden": 21550, "Someren": 9195, "Maasdonk": 5580, "Waalre": 8490, "Boxtel": 15260, "Reusel-De Mierden": 6200, "Laarbeek": 10790, "Waalwijk": 23340, "Heeze-Leende": 7585, "Bernheze": 14725, "Goirle": 11665, "Bergeijk": 9000, "Etten-Leur": 21390, "Asten": 7985, "Dongen": 12750, "Veldhoven": 22145, "Oisterwijk": 13105, "Roosendaal": 38990, "Sint-Oedenrode": 8995, "Woensdrecht": 10775, "Zundert": 10410, "'s-Hertogenbosch": 72875, "Grave": 6135, "Rucphen": 11055, "Eindhoven": 108150, "Sint-Michielsgestel": 13990, "Breda": 91825, "Eersel": 8995, "Haaren": 6610, "Sint Anthonis": 5660, "Valkenswaard": 15345, "Moerdijk": 18350, "Veghel": 18640, "Cuijk": 12405, "Drimmelen": 13360, "Schijndel": 11650, "Tilburg": 105675, "Helmond": 44485, "Woudrichem": 7215, "Oosterhout": 27280, "Mill en Sint Hubert": 5340, "Halderberge": 14770, "Loon op Zand": 11660, "Werkendam": 13220, "Cranendonck": 10080, "Son en Breugel": 8215, "Oirschot": 8900, "Aalburg": 6355, "Uden": 20640, "Hilvarenbeek": 7465, "Baarle-Nassau": 3255, "Vught": 12920, "Oss": 42515, "Best": 14280}, "Limburg": {"Simpelveld": 5465, "Roerdalen": 10410, "Voerendaal": 6255, "Roermond": 28800, "Mook en Middelaar": 3935, "Beek": 8380, "Nederweert": 8315, "Sittard-Geleen": 47565, "Nuth": 7885, "Horst aan de Maas": 20750, "Gulpen-Wittem": 7210, "Weert": 24385, "Heerlen": 44480, "Meerssen": 9770, "Vaals": 4905, "Kerkrade": 23460, "Onderbanken": 3955, "Schinnen": 6465, "Leudal": 17900, "Maasgouw": 11920, "Eijsden-Margraten": 12480, "Valkenburg aan de Geul": 8440, "Bergen (L.)": 6595, "Beesel": 6755, "Venlo": 50540, "Stein": 12775, "Venray": 21340, "Landgraaf": 19075, "Echt-Susteren": 15970, "Maastricht": 63635, "Brunssum": 14840, "Gennep": 8475, "Peel en Maas": 21360}, "Utrecht": {"Vianen": 9935, "Leusden": 14745, "Woudenberg": 6195, "Eemnes": 4440, "Bunschoten": 10230, "Woerden": 25605, "Wijk bij Duurstede": 11675, "Lopik": 6885, "De Bilt": 22020, "Nieuwegein": 30735, "Stichtse Vecht": 32605, "Rhenen": 9645, "Montfoort": 6805, "Baarn": 12600, "De Ronde Venen": 21485, "Zeist": 31615, "Houten": 24505, "Utrecht": 168860, "Oudewater": 5015, "Soest": 23335, "Utrechtse Heuvelrug": 24715, "Renswoude": 2465, "Veenendaal": 32200, "Bunnik": 7390, "Amersfoort": 76720, "IJsselstein": 17555}, "Zeeland": {"Sluis": 12075, "Veere": 10935, "Tholen": 12725, "Hulst": 13730, "Kapelle": 6285, "Borsele": 11170, "Noord-Beveland": 3760, "Goes": 18915, "Schouwen-Duiveland": 17100, "Vlissingen": 22305, "Terneuzen": 27530, "Reimerswaal": 10915, "Middelburg": 24495}}, "2008": {"Groningen": {"Winschoten": 9500, "De Marne": 5280, "Eemsmond": 8110, "Menterwolde": 6180, "Stadskanaal": 17110, "Marum": 4950, "Hoogezand-Sappemeer": 17460, "Winsum": 7020, "Bedum": 5250, "Scheemda": 7140, "Haren": 9910, "Delfzijl": 13640, "Leek": 9730, "Grootegast": 5980, "Groningen": 92320, "Reiderland": 3480, "Pekela": 6560, "Bellingwedde": 4770, "Slochteren": 7580, "Vlagtwedde": 8250, "Ten Boer": 3620, "Loppersum": 5290, "Appingedam": 6260, "Veendam": 14200, "Zuidhorn": 9200}, "Gelderland": {"Berkelland": 22390, "Neerijnen": 5860, "Oude IJsselstreek": 20030, "Renkum": 16480, "Buren": 12830, "Elburg": 11250, "Scherpenzeel": 4540, "Westervoort": 7800, "West Maas en Waal": 9160, "Brummen": 10720, "Ubbergen": 4740, "Neder-Betuwe": 11300, "Lingewaard": 22440, "Putten": 11770, "Lingewaal": 5440, "Winterswijk": 14660, "Heerde": 9200, "Rheden": 22650, "Rozendaal": 770, "Overbetuwe": 22260, "Lochem": 16880, "Culemborg": 13760, "Wageningen": 18440, "Hattem": 5980, "Harderwijk": 21470, "Duiven": 13060, "Doesburg": 5860, "Barneveld": 25870, "Nijkerk": 19560, "Voorst": 11850, "Arnhem": 72520, "Heumen": 8370, "Oldebroek": 11240, "Groesbeek": 9720, "Geldermalsen": 13270, "Apeldoorn": 78920, "Beuningen": 12630, "Doetinchem": 28430, "Zevenaar": 16160, "Epe": 16760, "Zaltbommel": 13140, "Druten": 9100, "Rijnwaarden": 5490, "Tiel": 20740, "Bronckhorst": 19070, "Ede": 54880, "Oost Gelre": 14700, "Zutphen": 23950, "Millingen aan de Rijn": 2950, "Ermelo": 13370, "Nunspeet": 13510, "Maasdriel": 11720, "Nijmegen": 84180, "Montferland": 17490, "Aalten": 13760, "Wijchen": 20040}, "Flevoland": {"Noordoostpolder": 22640, "Urk": 8840, "Lelystad": 36690, "Almere": 92420, "Dronten": 18960, "Zeewolde": 9970}, "Noord-Holland": {"Langedijk": 13070, "Muiden": 3380, "Haarlemmerliede en Spaarnwoude": 2750, "Weesp": 9040, "Zeevang": 3130, "Hilversum": 43200, "Velsen": 34190, "Wijdemeren": 11960, "Medemblik": 13190, "Castricum": 17740, "Hoorn": 34910, "Texel": 6830, "Naarden": 8960, "Zaanstad": 72410, "Aalsmeer": 13280, "Landsmeer": 5250, "Niedorp": 5940, "Drechterland": 9230, "Bloemendaal": 8940, "Anna Paulowna": 6980, "Ouder-Amstel": 6700, "Zandvoort": 8690, "Heerhugowaard": 24980, "Opmeer": 5590, "Heemstede": 13600, "Harenkarspel": 7770, "Heemskerk": 19620, "Waterland": 8550, "Bennebroek": 2680, "Wieringermeer": 6250, "Huizen": 21560, "Alkmaar": 47730, "Haarlemmermeer": 70690, "Schermer": 2590, "Heiloo": 11190, "Koggenland": 10660, "Den Helder": 29200, "Andijk": 3170, "Schagen": 9730, "Oostzaan": 4720, "Bergen (NH.)": 16130, "Amsterdam": 379580, "Uitgeest": 6070, "Edam-Volendam": 14160, "Diemen": 12330, "Bussum": 16750, "Purmerend": 40170, "Wormerland": 7960, "Beverwijk": 18990, "Zijpe": 5700, "Amstelveen": 41360, "Blaricum": 4680, "Graft-De Rijp": 3230, "Enkhuizen": 8950, "Laren": 5850, "Stede Broec": 10580, "Uithoorn": 13960, "Wieringen": 4290, "Beemster": 4210, "Haarlem": 75940, "Wervershoof": 4210}, "Friesland": {"Skarsterl\u00e2n": 13490, "Leeuwarderadeel": 5140, "W\u00fbnseradiel": 5810, "Ooststellingwerf": 13200, "Wymbritseradiel": 7840, "Ameland": 1710, "Harlingen": 7800, "Sneek": 16870, "Smallingerland": 27740, "Franekeradeel": 10180, "Weststellingwerf": 12820, "Terschelling": 2230, "Achtkarspelen": 13850, "Opsterland": 14820, "Dongeradeel": 12320, "Boarnsterhim": 9600, "Kollumerland en Nieuwkruisland": 6420, "Menaldumadeel": 6780, "het Bildt": 5360, "Bolsward": 5000, "Ferwerderadiel": 4310, "Gaasterl\u00e2n-Sleat": 5060, "Lemsterland": 6580, "Vlieland": 580, "Leeuwarden": 47420, "Tytsjerksteradiel": 16080, "Nijefurd": 5550, "Schiermonnikoog": 480, "Littenseradiel": 5380, "Heerenveen": 21980, "Dantumadeel": 9690}, "Zuid-Holland": {"Korendijk": 5460, "Capelle aan den IJssel": 33620, "Graafstroom": 4770, "Schoonhoven": 6120, "Alblasserdam": 9600, "Zoetermeer": 60920, "Wassenaar": 13500, "Waddinxveen": 12910, "Jacobswoude": 5280, "Hendrik-Ido-Ambacht": 12630, "'s-Gravenhage": 242020, "Katwijk": 30760, "Gorinchem": 17490, "Middelharnis": 9050, "Westvoorne": 7140, "Binnenmaas": 14490, "Noordwijkerhout": 7660, "Nieuw-Lekkerland": 4650, "Alphen aan den Rijn": 36340, "Albrandswaard": 11240, "Barendrecht": 22750, "Hillegom": 10300, "Westland": 49770, "Oud-Beijerland": 12140, "Rotterdam": 297640, "Leiden": 59940, "Zederik": 6740, "Midden-Delfland": 8540, "Giessenlanden": 7140, "Nederlek": 7310, "Voorschoten": 11910, "Bergambacht": 4800, "Cromstrijen": 6460, "Leidschendam-Voorburg": 38060, "Zoeterwoude": 4160, "Nieuwkoop": 13240, "Schiedam": 38170, "Nieuwerkerk aan den IJssel": 10920, "Oegstgeest": 11600, "Zwijndrecht": 22810, "Maassluis": 16030, "Lisse": 11240, "Rijswijk": 24740, "Dordrecht": 60220, "Oostflakkee": 5060, "Papendrecht": 16070, "Bodegraven": 9700, "Liesveld": 4880, "Leerdam": 10490, "Boskoop": 7600, "Vlaardingen": 36390, "Leiderdorp": 13570, "Ridderkerk": 22920, "Zevenhuizen-Moerkapelle": 5240, "Delft": 45750, "Reeuwijk": 6400, "Brielle": 7950, "Noordwijk": 12380, "Moordrecht": 4060, "Alkemade": 7200, "Rozenburg": 6300, "Lansingerland": 24720, "Pijnacker-Nootdorp": 21850, "Ouderkerk": 4090, "Goedereede": 5840, "Sliedrecht": 12180, "Krimpen aan den IJssel": 14720, "Spijkenisse": 37260, "Teylingen": 17660, "Hellevoetsluis": 19960, "Strijen": 4530, "Bernisse": 6240, "Hardinxveld-Giessendam": 8890, "Rijnwoude": 9250, "Gouda": 36240, "Dirksland": 4170, "Vlist": 4900}, "Drenthe": {"Hoogeveen": 27450, "Emmen": 55230, "De Wolden": 11760, "Aa en Hunze": 12930, "Noordenveld": 15780, "Coevorden": 18060, "Assen": 33500, "Midden-Drenthe": 16810, "Meppel": 16230, "Borger-Odoorn": 13130, "Tynaarlo": 16320, "Westerveld": 9720}, "Overijssel": {"Almelo": 36380, "Dalfsen": 13140, "Ommen": 8710, "Twenterand": 16570, "Hof van Twente": 17740, "Tubbergen": 10260, "Staphorst": 7760, "Dinkelland": 12840, "Oldenzaal": 15860, "Hengelo": 40880, "Zwolle": 59770, "Wierden": 11640, "Losser": 11240, "Haaksbergen": 12100, "Hellendoorn": 18010, "Steenwijkerland": 21660, "Hardenberg": 28760, "Enschede": 76120, "Kampen": 24940, "Olst-Wijhe": 8600, "Deventer": 49320, "Zwartewaterland": 10840, "Borne": 10440, "Rijssen-Holten": 18480, "Raalte": 18520}, "Noord-Brabant": {"Nuenen, Gerwen en Nederwetten": 11260, "Bladel": 9410, "Landerd": 7240, "Geldrop-Mierlo": 19200, "Steenbergen": 11560, "Boekel": 4720, "Gemert-Bakel": 13850, "Gilze en Rijen": 12660, "Alphen-Chaam": 4650, "Geertruidenberg": 10400, "Boxmeer": 14370, "Deurne": 15740, "Bergen op Zoom": 33070, "Heusden": 21310, "Someren": 8950, "Maasdonk": 5620, "Waalre": 8490, "Boxtel": 15250, "Reusel-De Mierden": 6080, "Laarbeek": 10790, "Waalwijk": 22960, "Heeze-Leende": 7490, "Bernheze": 14700, "Goirle": 11230, "Bergeijk": 8950, "Etten-Leur": 20420, "Asten": 8020, "Dongen": 12760, "Veldhoven": 21530, "Oisterwijk": 13080, "Roosendaal": 39130, "Sint-Oedenrode": 8640, "Woensdrecht": 10800, "Zundert": 10280, "'s-Hertogenbosch": 69430, "Grave": 6240, "Rucphen": 11220, "Eindhoven": 103880, "Sint-Michielsgestel": 14000, "Breda": 87800, "Eersel": 8880, "Haaren": 6770, "Sint Anthonis": 5750, "Valkenswaard": 15650, "Moerdijk": 18400, "Veghel": 18370, "Cuijk": 12020, "Drimmelen": 13310, "Schijndel": 11470, "Tilburg": 101880, "Helmond": 43300, "Woudrichem": 7190, "Oosterhout": 27240, "Mill en Sint Hubert": 5420, "Halderberge": 14790, "Loon op Zand": 11550, "Werkendam": 13200, "Cranendonck": 10010, "Son en Breugel": 7800, "Oirschot": 8790, "Aalburg": 6170, "Uden": 20090, "Hilvarenbeek": 7440, "Baarle-Nassau": 3280, "Vught": 12760, "Oss": 38450, "Best": 14550, "Lith": 3300}, "Limburg": {"Simpelveld": 5660, "Kerkrade": 24350, "Voerendaal": 6390, "Helden": 9640, "Mook en Middelaar": 4060, "Beek": 8540, "Nederweert": 8220, "Sittard-Geleen": 48740, "Roerdalen": 10570, "Nuth": 8030, "Meijel": 2960, "Horst aan de Maas": 14380, "Gulpen-Wittem": 7310, "Roermond": 27700, "Heerlen": 45600, "Meerssen": 10020, "Vaals": 4970, "Arcen en Velden": 4390, "Onderbanken": 4120, "Schinnen": 6690, "Leudal": 18270, "Maasgouw": 12280, "Valkenburg aan de Geul": 8630, "Kessel": 2100, "Bergen (L.)": 6760, "Beesel": 6800, "Margraten": 6690, "Meerlo-Wanssum": 3760, "Venlo": 46380, "Stein": 13080, "Eijsden": 5750, "Maasbree": 6350, "Sevenum": 3760, "Venray": 19360, "Weert": 24110, "Landgraaf": 19640, "Echt-Susteren": 16100, "Maastricht": 61370, "Brunssum": 15290, "Gennep": 8260}, "Utrecht": {"Vianen": 9940, "Leusden": 14500, "Woudenberg": 5800, "Eemnes": 4530, "Bunschoten": 9750, "Woerden": 24500, "Wijk bij Duurstede": 11770, "Lopik": 6890, "De Bilt": 22080, "Nieuwegein": 30820, "Rhenen": 9490, "Montfoort": 6740, "Baarn": 12700, "Abcoude": 4410, "De Ronde Venen": 17310, "Breukelen": 7460, "Zeist": 31400, "Houten": 23540, "Utrecht": 152340, "Oudewater": 5030, "Loenen": 4230, "Soest": 23380, "Utrechtse Heuvelrug": 25280, "Renswoude": 2260, "Veenendaal": 31470, "Bunnik": 7220, "Amersfoort": 72050, "Maarssen": 20080, "IJsselstein": 17380}, "Zeeland": {"Sluis": 12350, "Veere": 10960, "Tholen": 12600, "Hulst": 14000, "Kapelle": 6070, "Borsele": 11110, "Noord-Beveland": 3660, "Goes": 18820, "Schouwen-Duiveland": 17240, "Vlissingen": 22490, "Terneuzen": 27770, "Reimerswaal": 10580, "Middelburg": 24280}}, "2009": {"Groningen": {"Winschoten": 9510, "De Marne": 5230, "Eemsmond": 8100, "Menterwolde": 6180, "Stadskanaal": 16900, "Marum": 5000, "Hoogezand-Sappemeer": 17530, "Winsum": 7070, "Bedum": 5190, "Scheemda": 7150, "Haren": 9870, "Delfzijl": 13390, "Leek": 9800, "Grootegast": 5970, "Groningen": 93210, "Reiderland": 3440, "Pekela": 6530, "Bellingwedde": 4650, "Slochteren": 7630, "Vlagtwedde": 8230, "Ten Boer": 3710, "Loppersum": 5210, "Appingedam": 6260, "Veendam": 14130, "Zuidhorn": 9250}, "Gelderland": {"Berkelland": 22390, "Neerijnen": 5840, "Oude IJsselstreek": 20040, "Renkum": 16440, "Buren": 12790, "Elburg": 11190, "Scherpenzeel": 4600, "Westervoort": 7730, "West Maas en Waal": 9210, "Brummen": 10690, "Ubbergen": 4780, "Neder-Betuwe": 11360, "Lingewaard": 22690, "Putten": 11880, "Lingewaal": 5460, "Winterswijk": 14580, "Heerde": 9260, "Rheden": 22540, "Rozendaal": 780, "Overbetuwe": 22740, "Lochem": 17000, "Culemborg": 13850, "Wageningen": 18760, "Hattem": 6020, "Harderwijk": 21870, "Duiven": 13000, "Doesburg": 5870, "Barneveld": 26180, "Nijkerk": 19620, "Voorst": 11890, "Arnhem": 73360, "Heumen": 8390, "Oldebroek": 11190, "Groesbeek": 9740, "Geldermalsen": 13230, "Apeldoorn": 78860, "Beuningen": 12620, "Doetinchem": 28350, "Zevenaar": 16140, "Epe": 16740, "Zaltbommel": 13140, "Druten": 9100, "Rijnwaarden": 5510, "Tiel": 20660, "Bronckhorst": 19130, "Ede": 54860, "Oost Gelre": 14780, "Zutphen": 24070, "Millingen aan de Rijn": 2940, "Ermelo": 13390, "Nunspeet": 13550, "Maasdriel": 11790, "Nijmegen": 84400, "Montferland": 17580, "Aalten": 13690, "Wijchen": 20180}, "Flevoland": {"Noordoostpolder": 22620, "Urk": 8940, "Lelystad": 36970, "Almere": 93490, "Dronten": 19300, "Zeewolde": 10230}, "Noord-Holland": {"Langedijk": 13480, "Muiden": 3350, "Haarlemmerliede en Spaarnwoude": 2750, "Zeevang": 3130, "Hilversum": 43410, "Velsen": 34130, "Wijdemeren": 11910, "Medemblik": 13330, "Castricum": 17800, "Hoorn": 35250, "Texel": 6900, "Naarden": 8870, "Zaanstad": 73000, "Aalsmeer": 14090, "Landsmeer": 5250, "Niedorp": 5980, "Drechterland": 9380, "Bloemendaal": 11670, "Anna Paulowna": 6980, "Ouder-Amstel": 6720, "Zandvoort": 8670, "Heerhugowaard": 25220, "Opmeer": 5600, "Heemstede": 13630, "Harenkarspel": 7780, "Heemskerk": 19650, "Waterland": 8500, "Weesp": 9060, "Wieringermeer": 6240, "Huizen": 21650, "Alkmaar": 47490, "Haarlemmermeer": 71350, "Schermer": 2600, "Heiloo": 11260, "Koggenland": 10800, "Den Helder": 29010, "Andijk": 3140, "Schagen": 9600, "Oostzaan": 4720, "Bergen (NH.)": 16080, "Amsterdam": 383750, "Uitgeest": 6180, "Edam-Volendam": 14170, "Diemen": 12550, "Bussum": 16810, "Purmerend": 40330, "Wormerland": 7960, "Beverwijk": 19380, "Zijpe": 5730, "Amstelveen": 41710, "Blaricum": 4660, "Graft-De Rijp": 3210, "Enkhuizen": 9080, "Laren": 6070, "Stede Broec": 10540, "Uithoorn": 14020, "Wieringen": 4300, "Beemster": 4270, "Haarlem": 76170, "Wervershoof": 4260}, "Friesland": {"Skarsterl\u00e2n": 13540, "Leeuwarderadeel": 5140, "W\u00fbnseradiel": 5800, "Ooststellingwerf": 13100, "Wymbritseradiel": 7820, "Ameland": 1710, "Harlingen": 7840, "Sneek": 16870, "Smallingerland": 27860, "Franekeradeel": 10210, "Weststellingwerf": 12860, "Terschelling": 2250, "Dantumadiel": 9650, "Achtkarspelen": 13850, "Opsterland": 14910, "Dongeradeel": 12260, "Boarnsterhim": 9580, "Kollumerland en Nieuwkruisland": 6400, "Menaldumadeel": 6770, "het Bildt": 5300, "Bolsward": 5030, "Ferwerderadiel": 4290, "Gaasterl\u00e2n-Sleat": 5090, "Lemsterland": 6660, "Vlieland": 580, "Leeuwarden": 47830, "Tytsjerksteradiel": 16120, "Nijefurd": 5510, "Schiermonnikoog": 490, "Littenseradiel": 5400, "Heerenveen": 22090}, "Zuid-Holland": {"Korendijk": 5460, "Kaag en Braassem": 12520, "Capelle aan den IJssel": 33750, "Graafstroom": 4800, "Schoonhoven": 6070, "Alblasserdam": 9620, "Zoetermeer": 61640, "Wassenaar": 13550, "Waddinxveen": 12780, "Hendrik-Ido-Ambacht": 13190, "'s-Gravenhage": 244600, "Katwijk": 30810, "Gorinchem": 17570, "Middelharnis": 9170, "Westvoorne": 7090, "Binnenmaas": 14540, "Noordwijkerhout": 7610, "Nieuw-Lekkerland": 4660, "Alphen aan den Rijn": 36570, "Albrandswaard": 11480, "Barendrecht": 23200, "Hillegom": 10370, "Westland": 49840, "Oud-Beijerland": 12080, "Rotterdam": 299030, "Leiden": 59870, "Zederik": 6760, "Midden-Delfland": 8630, "Giessenlanden": 7120, "Nederlek": 7230, "Voorschoten": 11980, "Bergambacht": 4870, "Cromstrijen": 6450, "Leidschendam-Voorburg": 37920, "Zoeterwoude": 4120, "Nieuwkoop": 13230, "Schiedam": 38320, "Nieuwerkerk aan den IJssel": 10900, "Zwijndrecht": 22720, "Maassluis": 15990, "Lisse": 11310, "Rijswijk": 24710, "Dordrecht": 60230, "Oostflakkee": 5030, "Papendrecht": 16160, "Leerdam": 10550, "Liesveld": 4840, "Bodegraven": 9710, "Boskoop": 7580, "Vlaardingen": 36140, "Leiderdorp": 13670, "Ridderkerk": 22950, "Zevenhuizen-Moerkapelle": 5270, "Delft": 45900, "Reeuwijk": 6470, "Brielle": 7880, "Noordwijk": 12660, "Moordrecht": 4050, "Oegstgeest": 11690, "Rozenburg": 6240, "Lansingerland": 25570, "Pijnacker-Nootdorp": 22910, "Ouderkerk": 4090, "Goedereede": 5800, "Sliedrecht": 12230, "Krimpen aan den IJssel": 14780, "Spijkenisse": 36920, "Teylingen": 17840, "Hellevoetsluis": 19970, "Strijen": 4490, "Bernisse": 6240, "Hardinxveld-Giessendam": 8860, "Rijnwoude": 9250, "Gouda": 36190, "Dirksland": 4200, "Vlist": 4880}, "Drenthe": {"Hoogeveen": 27560, "Emmen": 55360, "De Wolden": 11740, "Aa en Hunze": 12910, "Noordenveld": 15770, "Coevorden": 18040, "Assen": 34000, "Midden-Drenthe": 16800, "Meppel": 16460, "Borger-Odoorn": 13090, "Tynaarlo": 16420, "Westerveld": 9700}, "Overijssel": {"Almelo": 36440, "Dalfsen": 13300, "Ommen": 8710, "Twenterand": 16620, "Hof van Twente": 17700, "Tubbergen": 10330, "Staphorst": 7790, "Dinkelland": 12810, "Oldenzaal": 15910, "Hengelo": 40850, "Zwolle": 60470, "Wierden": 11690, "Losser": 11290, "Haaksbergen": 12170, "Hellendoorn": 17920, "Steenwijkerland": 21600, "Hardenberg": 28990, "Enschede": 76700, "Kampen": 25160, "Olst-Wijhe": 8670, "Deventer": 49560, "Zwartewaterland": 10850, "Borne": 10570, "Rijssen-Holten": 18530, "Raalte": 18410}, "Noord-Brabant": {"Nuenen, Gerwen en Nederwetten": 11210, "Bladel": 9440, "Landerd": 7250, "Geldrop-Mierlo": 19190, "Steenbergen": 11570, "Boekel": 4750, "Gemert-Bakel": 14040, "Gilze en Rijen": 12710, "Alphen-Chaam": 4640, "Geertruidenberg": 10430, "Boxmeer": 14320, "Deurne": 15630, "Bergen op Zoom": 33230, "Heusden": 21430, "Someren": 8960, "Maasdonk": 5610, "Waalre": 8400, "Boxtel": 15240, "Reusel-De Mierden": 6090, "Laarbeek": 10750, "Waalwijk": 22990, "Heeze-Leende": 7530, "Bernheze": 14690, "Goirle": 11330, "Bergeijk": 8920, "Etten-Leur": 20680, "Asten": 7990, "Dongen": 12730, "Veldhoven": 21550, "Oisterwijk": 13050, "Roosendaal": 39260, "Sint-Oedenrode": 8740, "Woensdrecht": 10800, "Zundert": 10330, "'s-Hertogenbosch": 70060, "Grave": 6180, "Rucphen": 11240, "Eindhoven": 104700, "Sint-Michielsgestel": 14100, "Breda": 88240, "Eersel": 8890, "Haaren": 6710, "Sint Anthonis": 5750, "Valkenswaard": 15630, "Moerdijk": 18350, "Veghel": 18490, "Cuijk": 12100, "Drimmelen": 13320, "Schijndel": 11480, "Tilburg": 102500, "Helmond": 43740, "Woudrichem": 7170, "Oosterhout": 27510, "Mill en Sint Hubert": 5410, "Halderberge": 14680, "Loon op Zand": 11590, "Werkendam": 13180, "Cranendonck": 10000, "Son en Breugel": 7850, "Oirschot": 8740, "Aalburg": 6250, "Uden": 20240, "Hilvarenbeek": 7420, "Baarle-Nassau": 3260, "Vught": 12740, "Oss": 38620, "Best": 14540, "Lith": 3270}, "Limburg": {"Simpelveld": 5590, "Kerkrade": 24190, "Voerendaal": 6380, "Helden": 9650, "Mook en Middelaar": 4030, "Beek": 8500, "Nederweert": 8250, "Sittard-Geleen": 48580, "Roerdalen": 10680, "Nuth": 7990, "Meijel": 2980, "Horst aan de Maas": 14550, "Gulpen-Wittem": 7240, "Roermond": 27810, "Heerlen": 45310, "Meerssen": 10000, "Vaals": 4960, "Arcen en Velden": 4380, "Onderbanken": 4090, "Schinnen": 6700, "Leudal": 18220, "Maasgouw": 12260, "Valkenburg aan de Geul": 8640, "Kessel": 2090, "Bergen (L.)": 6700, "Beesel": 6870, "Margraten": 6570, "Meerlo-Wanssum": 3810, "Venlo": 46160, "Stein": 12950, "Eijsden": 5700, "Maasbree": 6410, "Sevenum": 3770, "Venray": 19430, "Weert": 24150, "Landgraaf": 19670, "Echt-Susteren": 16030, "Maastricht": 61520, "Brunssum": 15160, "Gennep": 8360}, "Utrecht": {"Vianen": 9990, "Leusden": 14540, "Woudenberg": 5840, "Eemnes": 4480, "Bunschoten": 9830, "Woerden": 24710, "Wijk bij Duurstede": 11750, "Lopik": 6960, "De Bilt": 22030, "Nieuwegein": 30730, "Rhenen": 9510, "Montfoort": 6740, "Baarn": 12660, "Abcoude": 4420, "De Ronde Venen": 17330, "Breukelen": 7440, "Zeist": 31360, "Houten": 23920, "Utrecht": 154970, "Oudewater": 5020, "Loenen": 4320, "Soest": 23490, "Utrechtse Heuvelrug": 25270, "Renswoude": 2290, "Veenendaal": 31560, "Bunnik": 7300, "Amersfoort": 72910, "Maarssen": 20230, "IJsselstein": 17460}, "Zeeland": {"Sluis": 12300, "Veere": 10940, "Tholen": 12640, "Hulst": 14010, "Kapelle": 6180, "Borsele": 11120, "Noord-Beveland": 3680, "Goes": 18850, "Schouwen-Duiveland": 17200, "Vlissingen": 22400, "Terneuzen": 27740, "Reimerswaal": 10620, "Middelburg": 24340}}, "2011": {"Groningen": {"Oldambt": 19945, "Stadskanaal": 16770, "Eemsmond": 8030, "Menterwolde": 6080, "De Marne": 5165, "Marum": 5075, "Hoogezand-Sappemeer": 17665, "Winsum": 7050, "Bedum": 5215, "Haren": 9780, "Delfzijl": 13270, "Leek": 9770, "Grootegast": 5955, "Groningen": 95925, "Pekela": 6455, "Bellingwedde": 4665, "Slochteren": 7615, "Vlagtwedde": 8165, "Ten Boer": 3710, "Loppersum": 5135, "Appingedam": 6220, "Veendam": 14095, "Zuidhorn": 9350}, "Gelderland": {"Berkelland": 22315, "Neerijnen": 5865, "Oude IJsselstreek": 20000, "Renkum": 16350, "Buren": 13005, "Elburg": 11300, "Scherpenzeel": 4700, "Westervoort": 7735, "West Maas en Waal": 9150, "Brummen": 10755, "Ubbergen": 4755, "Neder-Betuwe": 11360, "Lingewaard": 23005, "Putten": 11980, "Lingewaal": 5440, "Winterswijk": 14615, "Heerde": 9275, "Rheden": 22660, "Rozendaal": 760, "Overbetuwe": 23095, "Lochem": 16905, "Culemborg": 13910, "Wageningen": 19055, "Hattem": 6010, "Harderwijk": 22815, "Duiven": 13015, "Doesburg": 5945, "Barneveld": 26660, "Nijkerk": 19995, "Voorst": 11865, "Arnhem": 74565, "Heumen": 8315, "Oldebroek": 11210, "Groesbeek": 9650, "Geldermalsen": 13225, "Apeldoorn": 79110, "Beuningen": 12770, "Doetinchem": 28310, "Zevenaar": 16380, "Epe": 16685, "Zaltbommel": 13345, "Druten": 9090, "Rijnwaarden": 5545, "Tiel": 20735, "Bronckhorst": 18970, "Ede": 55140, "Oost Gelre": 14780, "Zutphen": 24120, "Millingen aan de Rijn": 2960, "Ermelo": 13275, "Nunspeet": 13515, "Maasdriel": 11875, "Nijmegen": 85640, "Montferland": 17555, "Aalten": 13680, "Wijchen": 20540}, "Flevoland": {"Noordoostpolder": 22805, "Urk": 9245, "Lelystad": 37590, "Almere": 96015, "Dronten": 19860, "Zeewolde": 10385}, "Noord-Holland": {"Langedijk": 13530, "Muiden": 3330, "Haarlemmerliede en Spaarnwoude": 2745, "Zeevang": 3175, "Hilversum": 43665, "Velsen": 34055, "Wijdemeren": 11915, "Medemblik": 21070, "Castricum": 17680, "Hoorn": 35795, "Texel": 6925, "Naarden": 8945, "Zaanstad": 74395, "Aalsmeer": 15235, "Landsmeer": 5325, "Niedorp": 6030, "Drechterland": 9520, "Bloemendaal": 11585, "Anna Paulowna": 7045, "Ouder-Amstel": 6750, "Zandvoort": 8620, "Heerhugowaard": 25825, "Opmeer": 5665, "Heemstede": 13975, "Harenkarspel": 7890, "Heemskerk": 19970, "Waterland": 8580, "Weesp": 9280, "Wieringermeer": 6205, "Huizen": 21490, "Alkmaar": 47645, "Haarlemmermeer": 72065, "Schermer": 2635, "Heiloo": 11445, "Koggenland": 10970, "Den Helder": 28820, "Schagen": 9570, "Oostzaan": 4660, "Bergen (NH.)": 15870, "Amsterdam": 396005, "Uitgeest": 6365, "Edam-Volendam": 14260, "Diemen": 12920, "Bussum": 17055, "Purmerend": 40510, "Wormerland": 7900, "Beverwijk": 19920, "Zijpe": 5725, "Amstelveen": 42875, "Blaricum": 4630, "Graft-De Rijp": 3230, "Enkhuizen": 9080, "Laren": 5995, "Stede Broec": 10590, "Uithoorn": 14260, "Wieringen": 4270, "Beemster": 4280, "Haarlem": 77410}, "Friesland": {"Skarsterl\u00e2n": 13650, "Leeuwarderadeel": 5155, "Ooststellingwerf": 12980, "Ameland": 1750, "Harlingen": 7920, "Smallingerland": 27945, "Franekeradeel": 10280, "Weststellingwerf": 12900, "Terschelling": 2235, "Dantumadiel": 9650, "Achtkarspelen": 13855, "Opsterland": 14995, "Dongeradeel": 12100, "Boarnsterhim": 9595, "Kollumerland en Nieuwkruisland": 6295, "het Bildt": 5325, "Ferwerderadiel": 4320, "Heerenveen": 22105, "Lemsterland": 6700, "Menameradiel": 6795, "Vlieland": 575, "Leeuwarden": 48435, "Tytsjerksteradiel": 16130, "Schiermonnikoog": 485, "Littenseradiel": 5400, "S\u00fadwest-Frysl\u00e2n": 41215, "Gaasterl\u00e2n-Sleat": 5055}, "Zuid-Holland": {"Korendijk": 5405, "Kaag en Braassem": 12710, "Capelle aan den IJssel": 34145, "Graafstroom": 4770, "Schoonhoven": 6055, "Alblasserdam": 9815, "Zoetermeer": 62175, "Wassenaar": 13535, "Waddinxveen": 12725, "Hendrik-Ido-Ambacht": 14100, "'s-Gravenhage": 251045, "Katwijk": 31150, "Gorinchem": 17780, "Middelharnis": 9205, "Binnenmaas": 14600, "Noordwijkerhout": 7725, "Nieuw-Lekkerland": 4660, "Alphen aan den Rijn": 36800, "Barendrecht": 23685, "Hillegom": 10450, "Westland": 50090, "Oud-Beijerland": 12000, "Rotterdam": 310065, "Leiden": 60390, "Zederik": 6710, "Midden-Delfland": 8965, "Giessenlanden": 7100, "Bodegraven-Reeuwijk": 16350, "Nederlek": 7075, "Voorschoten": 12410, "Bergambacht": 4960, "Cromstrijen": 6440, "Leidschendam-Voorburg": 37625, "Zoeterwoude": 4085, "Nieuwkoop": 13330, "Schiedam": 38470, "Zuidplas": 20400, "Zwijndrecht": 22825, "Maassluis": 16250, "Pijnacker-Nootdorp": 24625, "Dordrecht": 60285, "Albrandswaard": 12425, "Papendrecht": 16240, "Leerdam": 10545, "Liesveld": 4845, "Lisse": 11525, "Boskoop": 7535, "Vlaardingen": 36470, "Leiderdorp": 13740, "Ridderkerk": 23135, "Delft": 46040, "Westvoorne": 7045, "Brielle": 8020, "Noordwijk": 12625, "Oostflakkee": 5195, "Oegstgeest": 11835, "Rijswijk": 24640, "Lansingerland": 27165, "Ouderkerk": 4105, "Goedereede": 5775, "Sliedrecht": 12250, "Krimpen aan den IJssel": 14705, "Spijkenisse": 36805, "Teylingen": 17935, "Hellevoetsluis": 19890, "Strijen": 4435, "Bernisse": 6170, "Hardinxveld-Giessendam": 8810, "Rijnwoude": 9140, "Gouda": 36310, "Dirksland": 4220, "Vlist": 4920}, "Drenthe": {"Hoogeveen": 27640, "Emmen": 55220, "De Wolden": 11795, "Aa en Hunze": 12945, "Noordenveld": 15575, "Coevorden": 18095, "Assen": 34350, "Midden-Drenthe": 16830, "Meppel": 16675, "Borger-Odoorn": 12990, "Tynaarlo": 16510, "Westerveld": 9710}, "Overijssel": {"Almelo": 36610, "Dalfsen": 13430, "Ommen": 8660, "Twenterand": 16655, "Hof van Twente": 17925, "Tubbergen": 10425, "Staphorst": 7865, "Dinkelland": 12840, "Oldenzaal": 16165, "Hengelo": 40630, "Zwolle": 61660, "Wierden": 11795, "Losser": 11285, "Haaksbergen": 12185, "Hellendoorn": 17905, "Steenwijkerland": 21615, "Hardenberg": 29265, "Enschede": 77715, "Kampen": 25370, "Olst-Wijhe": 8660, "Deventer": 50110, "Zwartewaterland": 10870, "Borne": 10765, "Rijssen-Holten": 18815, "Raalte": 18345}, "Noord-Brabant": {"Nuenen, Gerwen en Nederwetten": 11165, "Bladel": 9505, "Landerd": 7270, "Geldrop-Mierlo": 19390, "Steenbergen": 11590, "Boekel": 4825, "Gemert-Bakel": 14280, "Gilze en Rijen": 12720, "Alphen-Chaam": 4665, "Geertruidenberg": 10720, "Boxmeer": 14270, "Deurne": 15750, "Bergen op Zoom": 33435, "Heusden": 21520, "Someren": 9030, "Maasdonk": 5610, "Waalre": 8355, "Boxtel": 15265, "Reusel-De Mierden": 6190, "Laarbeek": 10640, "Waalwijk": 23215, "Heeze-Leende": 7575, "Bernheze": 14765, "Goirle": 11505, "Bergeijk": 8900, "Etten-Leur": 21110, "Asten": 7955, "Dongen": 12620, "Veldhoven": 21840, "Oisterwijk": 13090, "Roosendaal": 39240, "Sint-Oedenrode": 8930, "Woensdrecht": 10780, "Zundert": 10355, "'s-Hertogenbosch": 71585, "Grave": 6310, "Rucphen": 11225, "Eindhoven": 106060, "Sint-Michielsgestel": 14000, "Breda": 89595, "Eersel": 8930, "Haaren": 6675, "Sint Anthonis": 5745, "Valkenswaard": 15495, "Moerdijk": 18300, "Veghel": 18630, "Cuijk": 12270, "Drimmelen": 13255, "Schijndel": 11535, "Tilburg": 103875, "Helmond": 44160, "Woudrichem": 7195, "Oosterhout": 27470, "Mill en Sint Hubert": 5400, "Halderberge": 14705, "Loon op Zand": 11630, "Werkendam": 13185, "Cranendonck": 10080, "Son en Breugel": 7915, "Oirschot": 8785, "Aalburg": 6310, "Uden": 20495, "Hilvarenbeek": 7430, "Baarle-Nassau": 3280, "Vught": 12905, "Oss": 42105, "Best": 14425}, "Limburg": {"Simpelveld": 5515, "Roerdalen": 10615, "Voerendaal": 6365, "Roermond": 28180, "Mook en Middelaar": 3980, "Beek": 8490, "Nederweert": 8260, "Sittard-Geleen": 48245, "Nuth": 7940, "Horst aan de Maas": 20685, "Gulpen-Wittem": 7185, "Weert": 24245, "Heerlen": 45090, "Meerssen": 9920, "Vaals": 4985, "Kerkrade": 23795, "Onderbanken": 4040, "Schinnen": 6640, "Leudal": 18115, "Maasgouw": 12135, "Eijsden-Margraten": 12455, "Valkenburg aan de Geul": 8585, "Bergen (L.)": 6670, "Beesel": 6860, "Venlo": 50385, "Stein": 12890, "Venray": 21265, "Landgraaf": 19425, "Echt-Susteren": 16065, "Maastricht": 62125, "Brunssum": 15065, "Gennep": 8475, "Peel en Maas": 21290}, "Utrecht": {"Vianen": 9975, "Leusden": 14610, "Woudenberg": 6005, "Eemnes": 4475, "Bunschoten": 10030, "Woerden": 25120, "Wijk bij Duurstede": 11670, "Lopik": 6955, "De Bilt": 22095, "Nieuwegein": 30755, "Stichtse Vecht": 32175, "Rhenen": 9560, "Montfoort": 6735, "Baarn": 12665, "De Ronde Venen": 21650, "Zeist": 31500, "Houten": 24255, "Utrecht": 160795, "Oudewater": 4975, "Soest": 23490, "Utrechtse Heuvelrug": 25185, "Renswoude": 2390, "Veenendaal": 31700, "Bunnik": 7305, "Amersfoort": 74615, "IJsselstein": 17585}, "Zeeland": {"Sluis": 12210, "Veere": 10970, "Tholen": 12705, "Hulst": 13910, "Kapelle": 6225, "Borsele": 11200, "Noord-Beveland": 3730, "Goes": 18780, "Schouwen-Duiveland": 17310, "Vlissingen": 22345, "Terneuzen": 27530, "Reimerswaal": 10790, "Middelburg": 24645}}, "2010": {"Groningen": {"Oldambt": 20030, "Stadskanaal": 16910, "Eemsmond": 8075, "Menterwolde": 6170, "De Marne": 5195, "Marum": 5060, "Hoogezand-Sappemeer": 17595, "Winsum": 7045, "Bedum": 5205, "Haren": 9795, "Delfzijl": 13300, "Leek": 9795, "Grootegast": 5930, "Groningen": 94625, "Pekela": 6505, "Bellingwedde": 4620, "Slochteren": 7605, "Vlagtwedde": 8200, "Ten Boer": 3700, "Loppersum": 5140, "Appingedam": 6240, "Veendam": 14115, "Zuidhorn": 9330}, "Gelderland": {"Berkelland": 22330, "Neerijnen": 5860, "Oude IJsselstreek": 19950, "Renkum": 16385, "Buren": 12935, "Elburg": 11245, "Scherpenzeel": 4690, "Westervoort": 7675, "West Maas en Waal": 9230, "Brummen": 10700, "Ubbergen": 4750, "Neder-Betuwe": 11320, "Lingewaard": 22880, "Putten": 11915, "Lingewaal": 5445, "Winterswijk": 14610, "Heerde": 9275, "Rheden": 22490, "Rozendaal": 745, "Overbetuwe": 22945, "Lochem": 16990, "Culemborg": 13865, "Wageningen": 19170, "Hattem": 6035, "Harderwijk": 22340, "Duiven": 13045, "Doesburg": 5925, "Barneveld": 26390, "Nijkerk": 19860, "Voorst": 11910, "Arnhem": 74050, "Heumen": 8395, "Oldebroek": 11205, "Groesbeek": 9690, "Geldermalsen": 13245, "Apeldoorn": 78970, "Beuningen": 12725, "Doetinchem": 28365, "Zevenaar": 16210, "Epe": 16670, "Zaltbommel": 13260, "Druten": 9085, "Rijnwaarden": 5550, "Tiel": 20720, "Bronckhorst": 19035, "Ede": 54905, "Oost Gelre": 14760, "Zutphen": 24080, "Millingen aan de Rijn": 2960, "Ermelo": 13345, "Nunspeet": 13550, "Maasdriel": 11785, "Nijmegen": 84865, "Montferland": 17630, "Aalten": 13735, "Wijchen": 20305}, "Flevoland": {"Noordoostpolder": 22730, "Urk": 9065, "Lelystad": 37360, "Almere": 94650, "Dronten": 19605, "Zeewolde": 10285}, "Noord-Holland": {"Langedijk": 13520, "Muiden": 3330, "Haarlemmerliede en Spaarnwoude": 2730, "Zeevang": 3155, "Hilversum": 43460, "Velsen": 33975, "Wijdemeren": 11950, "Medemblik": 13525, "Castricum": 17720, "Hoorn": 35670, "Texel": 6945, "Naarden": 8965, "Zaanstad": 73635, "Aalsmeer": 14705, "Landsmeer": 5320, "Niedorp": 5975, "Drechterland": 9505, "Bloemendaal": 11615, "Anna Paulowna": 7010, "Ouder-Amstel": 6725, "Zandvoort": 8665, "Heerhugowaard": 25380, "Opmeer": 5635, "Heemstede": 13845, "Harenkarspel": 7835, "Heemskerk": 19805, "Waterland": 8530, "Weesp": 9075, "Wieringermeer": 6230, "Huizen": 21595, "Alkmaar": 47635, "Haarlemmermeer": 71790, "Schermer": 2610, "Heiloo": 11345, "Koggenland": 10890, "Den Helder": 28895, "Andijk": 3135, "Schagen": 9615, "Oostzaan": 4695, "Bergen (NH.)": 15965, "Amsterdam": 389265, "Uitgeest": 6300, "Edam-Volendam": 14205, "Diemen": 12740, "Bussum": 16890, "Purmerend": 40375, "Wormerland": 7935, "Beverwijk": 19675, "Zijpe": 5760, "Amstelveen": 42260, "Blaricum": 4630, "Graft-De Rijp": 3235, "Enkhuizen": 9075, "Laren": 5955, "Stede Broec": 10515, "Uithoorn": 14230, "Wieringen": 4285, "Beemster": 4290, "Haarlem": 76835, "Wervershoof": 4320}, "Friesland": {"Skarsterl\u00e2n": 13605, "Leeuwarderadeel": 5160, "W\u00fbnseradiel": 5775, "Ooststellingwerf": 13080, "Wymbritseradiel": 7840, "Ameland": 1740, "Harlingen": 7905, "Sneek": 16980, "Smallingerland": 27860, "Franekeradeel": 10200, "Weststellingwerf": 12875, "Terschelling": 2250, "Dantumadiel": 9615, "Achtkarspelen": 13825, "Opsterland": 15045, "Dongeradeel": 12175, "Boarnsterhim": 9590, "Kollumerland en Nieuwkruisland": 6345, "Menaldumadeel": 6775, "het Bildt": 5315, "Bolsward": 5050, "Ferwerderadiel": 4305, "Gaasterl\u00e2n-Sleat": 5085, "Lemsterland": 6695, "Vlieland": 575, "Leeuwarden": 48155, "Tytsjerksteradiel": 16125, "Nijefurd": 5510, "Schiermonnikoog": 480, "Littenseradiel": 5370, "Heerenveen": 22090}, "Zuid-Holland": {"Korendijk": 5445, "Kaag en Braassem": 12645, "Capelle aan den IJssel": 33785, "Graafstroom": 4770, "Schoonhoven": 6090, "Alblasserdam": 9725, "Zoetermeer": 61990, "Wassenaar": 13495, "Waddinxveen": 12785, "Hendrik-Ido-Ambacht": 13705, "'s-Gravenhage": 247855, "Katwijk": 31050, "Gorinchem": 17655, "Middelharnis": 9145, "Westvoorne": 7060, "Binnenmaas": 14575, "Noordwijkerhout": 7705, "Nieuw-Lekkerland": 4665, "Alphen aan den Rijn": 36765, "Barendrecht": 23490, "Hillegom": 10370, "Westland": 50005, "Oud-Beijerland": 12000, "Rotterdam": 301420, "Leiden": 60050, "Zederik": 6770, "Midden-Delfland": 8795, "Giessenlanden": 7100, "Nederlek": 7150, "Voorschoten": 12215, "Bergambacht": 4925, "Cromstrijen": 6445, "Leidschendam-Voorburg": 37695, "Zoeterwoude": 4085, "Nieuwkoop": 13290, "Schiedam": 38445, "Zuidplas": 20325, "Zwijndrecht": 22785, "Maassluis": 16075, "Lisse": 11345, "Rijswijk": 24660, "Dordrecht": 60165, "Albrandswaard": 12140, "Papendrecht": 16240, "Leerdam": 10580, "Liesveld": 4825, "Bodegraven": 9690, "Boskoop": 7545, "Vlaardingen": 36135, "Leiderdorp": 13640, "Ridderkerk": 23020, "Delft": 45910, "Reeuwijk": 6525, "Brielle": 7895, "Noordwijk": 12650, "Oostflakkee": 5155, "Oegstgeest": 11715, "Rozenburg": 6255, "Lansingerland": 26330, "Pijnacker-Nootdorp": 23975, "Ouderkerk": 4085, "Goedereede": 5755, "Sliedrecht": 12265, "Krimpen aan den IJssel": 14770, "Spijkenisse": 36845, "Teylingen": 17950, "Hellevoetsluis": 20005, "Strijen": 4455, "Bernisse": 6190, "Hardinxveld-Giessendam": 8810, "Rijnwoude": 9175, "Gouda": 36360, "Dirksland": 4245, "Vlist": 4875}, "Drenthe": {"Hoogeveen": 27635, "Emmen": 55365, "De Wolden": 11770, "Aa en Hunze": 12880, "Noordenveld": 15565, "Coevorden": 18125, "Assen": 34250, "Midden-Drenthe": 16810, "Meppel": 16590, "Borger-Odoorn": 13035, "Tynaarlo": 16495, "Westerveld": 9685}, "Overijssel": {"Almelo": 36545, "Dalfsen": 13405, "Ommen": 8685, "Twenterand": 16585, "Hof van Twente": 17865, "Tubbergen": 10435, "Staphorst": 7860, "Dinkelland": 12825, "Oldenzaal": 16045, "Hengelo": 40665, "Zwolle": 61095, "Wierden": 11690, "Losser": 11290, "Haaksbergen": 12190, "Hellendoorn": 17890, "Steenwijkerland": 21615, "Hardenberg": 29160, "Enschede": 77215, "Kampen": 25215, "Olst-Wijhe": 8675, "Deventer": 49925, "Zwartewaterland": 10855, "Borne": 10650, "Rijssen-Holten": 18635, "Raalte": 18360}, "Noord-Brabant": {"Nuenen, Gerwen en Nederwetten": 11135, "Bladel": 9440, "Landerd": 7260, "Geldrop-Mierlo": 19250, "Steenbergen": 11545, "Boekel": 4805, "Gemert-Bakel": 14190, "Gilze en Rijen": 12750, "Alphen-Chaam": 4655, "Geertruidenberg": 10595, "Boxmeer": 14260, "Deurne": 15700, "Bergen op Zoom": 33330, "Heusden": 21415, "Someren": 8975, "Maasdonk": 5630, "Waalre": 8380, "Boxtel": 15250, "Reusel-De Mierden": 6140, "Laarbeek": 10670, "Waalwijk": 23000, "Heeze-Leende": 7560, "Bernheze": 14725, "Goirle": 11475, "Bergeijk": 8910, "Etten-Leur": 20980, "Asten": 7965, "Dongen": 12625, "Veldhoven": 21695, "Oisterwijk": 13090, "Roosendaal": 39290, "Sint-Oedenrode": 8870, "Woensdrecht": 10770, "Zundert": 10315, "'s-Hertogenbosch": 70980, "Grave": 6275, "Rucphen": 11220, "Eindhoven": 105315, "Sint-Michielsgestel": 14035, "Breda": 88850, "Eersel": 8900, "Haaren": 6655, "Sint Anthonis": 5775, "Valkenswaard": 15550, "Moerdijk": 18315, "Veghel": 18580, "Cuijk": 12200, "Drimmelen": 13300, "Schijndel": 11515, "Tilburg": 103160, "Helmond": 44040, "Woudrichem": 7195, "Oosterhout": 27515, "Mill en Sint Hubert": 5405, "Halderberge": 14695, "Loon op Zand": 11635, "Werkendam": 13160, "Cranendonck": 10085, "Son en Breugel": 7890, "Oirschot": 8710, "Aalburg": 6300, "Uden": 20350, "Hilvarenbeek": 7405, "Baarle-Nassau": 3265, "Vught": 12805, "Oss": 38760, "Best": 14500, "Lith": 3265}, "Limburg": {"Simpelveld": 5560, "Roerdalen": 10655, "Voerendaal": 6360, "Roermond": 28025, "Mook en Middelaar": 4030, "Beek": 8515, "Nederweert": 8195, "Sittard-Geleen": 48455, "Nuth": 7965, "Horst aan de Maas": 20480, "Gulpen-Wittem": 7240, "Weert": 24225, "Heerlen": 45180, "Meerssen": 9950, "Vaals": 4970, "Kerkrade": 23960, "Onderbanken": 4080, "Schinnen": 6700, "Leudal": 18170, "Maasgouw": 12190, "Valkenburg aan de Geul": 8660, "Bergen (L.)": 6690, "Beesel": 6905, "Margraten": 6640, "Venlo": 50585, "Stein": 12865, "Eijsden": 5730, "Venray": 21205, "Landgraaf": 19540, "Echt-Susteren": 16050, "Maastricht": 61575, "Brunssum": 15120, "Gennep": 8400, "Peel en Maas": 21225}, "Utrecht": {"Vianen": 9975, "Leusden": 14640, "Woudenberg": 5935, "Eemnes": 4460, "Bunschoten": 9970, "Woerden": 24950, "Wijk bij Duurstede": 11700, "Lopik": 6965, "De Bilt": 22080, "Nieuwegein": 30695, "Rhenen": 9530, "Montfoort": 6740, "Baarn": 12660, "Abcoude": 4470, "De Ronde Venen": 17260, "Breukelen": 7390, "Zeist": 31260, "Houten": 24105, "Utrecht": 158530, "Oudewater": 4985, "Loenen": 4340, "Soest": 23470, "Utrechtse Heuvelrug": 25205, "Renswoude": 2315, "Veenendaal": 31565, "Bunnik": 7330, "Amersfoort": 73775, "Maarssen": 20295, "IJsselstein": 17525}, "Zeeland": {"Sluis": 12270, "Veere": 10915, "Tholen": 12650, "Hulst": 13985, "Kapelle": 6240, "Borsele": 11155, "Noord-Beveland": 3705, "Goes": 18790, "Schouwen-Duiveland": 17295, "Vlissingen": 22325, "Terneuzen": 27590, "Reimerswaal": 10735, "Middelburg": 24565}}, "2013": {"Groningen": {"Oldambt": 19620, "Stadskanaal": 16635, "Eemsmond": 7865, "Menterwolde": 6090, "De Marne": 5075, "Marum": 5070, "Hoogezand-Sappemeer": 17480, "Winsum": 6995, "Bedum": 5270, "Haren": 9825, "Delfzijl": 12990, "Leek": 9890, "Grootegast": 5990, "Groningen": 98435, "Pekela": 6370, "Bellingwedde": 4495, "Slochteren": 7685, "Vlagtwedde": 8105, "Ten Boer": 3745, "Loppersum": 5085, "Appingedam": 6215, "Veendam": 14095, "Zuidhorn": 9380}, "Gelderland": {"Berkelland": 22235, "Neerijnen": 5965, "Oude IJsselstreek": 19880, "Renkum": 16275, "Buren": 12960, "Elburg": 11370, "Scherpenzeel": 4760, "Westervoort": 7670, "West Maas en Waal": 9255, "Brummen": 10745, "Ubbergen": 4800, "Neder-Betuwe": 11360, "Lingewaard": 23080, "Putten": 12070, "Lingewaal": 5525, "Winterswijk": 14550, "Heerde": 9355, "Rheden": 22375, "Rozendaal": 755, "Overbetuwe": 23445, "Lochem": 16965, "Culemborg": 13935, "Wageningen": 19385, "Hattem": 6015, "Harderwijk": 23185, "Duiven": 13035, "Doesburg": 5890, "Barneveld": 27030, "Nijkerk": 20260, "Voorst": 11840, "Arnhem": 75465, "Heumen": 8290, "Oldebroek": 11300, "Groesbeek": 9685, "Geldermalsen": 13230, "Apeldoorn": 79700, "Beuningen": 12690, "Doetinchem": 28545, "Zevenaar": 16460, "Epe": 16410, "Zaltbommel": 13450, "Druten": 9165, "Rijnwaarden": 5510, "Tiel": 20975, "Bronckhorst": 18740, "Ede": 55945, "Oost Gelre": 14650, "Zutphen": 24175, "Millingen aan de Rijn": 2980, "Ermelo": 13235, "Nunspeet": 13495, "Maasdriel": 11930, "Nijmegen": 86760, "Montferland": 17465, "Aalten": 13555, "Wijchen": 20770}, "Flevoland": {"Noordoostpolder": 22875, "Urk": 9475, "Lelystad": 37950, "Almere": 98285, "Dronten": 20055, "Zeewolde": 10485}, "Noord-Holland": {"Langedijk": 13465, "Muiden": 3280, "Haarlemmerliede en Spaarnwoude": 2795, "Zeevang": 3155, "Hilversum": 44080, "Velsen": 33840, "Wijdemeren": 11865, "Medemblik": 21215, "Castricum": 17555, "Hoorn": 36255, "Texel": 6895, "Naarden": 8945, "Zaanstad": 75620, "Aalsmeer": 15440, "Landsmeer": 5440, "Drechterland": 9510, "Bloemendaal": 11660, "Ouder-Amstel": 6795, "Zandvoort": 8640, "Heerhugowaard": 26275, "Opmeer": 5650, "Heemstede": 13945, "Heemskerk": 19905, "Waterland": 8585, "Weesp": 9360, "Huizen": 21280, "Alkmaar": 47955, "Haarlemmermeer": 72440, "Schermer": 2695, "Heiloo": 11460, "Koggenland": 11145, "Den Helder": 28755, "Schagen": 23080, "Oostzaan": 4675, "Bergen (NH.)": 15650, "Amsterdam": 406015, "Uitgeest": 6500, "Edam-Volendam": 14400, "Diemen": 12990, "Bussum": 17080, "Purmerend": 40595, "Wormerland": 7880, "Beverwijk": 20210, "Amstelveen": 44150, "Blaricum": 4715, "Graft-De Rijp": 3200, "Enkhuizen": 9130, "Laren": 5810, "Stede Broec": 10590, "Uithoorn": 14415, "Hollands Kroon": 23560, "Beemster": 4390, "Haarlem": 78435}, "Friesland": {"Skarsterl\u00e2n": 13690, "Leeuwarderadeel": 5125, "Ooststellingwerf": 12900, "Ameland": 1775, "Harlingen": 7880, "Smallingerland": 27850, "Franekeradeel": 10200, "Weststellingwerf": 12745, "Terschelling": 2260, "Dantumadiel": 9545, "Achtkarspelen": 13830, "Opsterland": 14960, "Dongeradeel": 12075, "Boarnsterhim": 9725, "Kollumerland en Nieuwkruisland": 6230, "het Bildt": 5205, "Ferwerderadiel": 4330, "Heerenveen": 21965, "Lemsterland": 6675, "Menameradiel": 6715, "Vlieland": 565, "Leeuwarden": 48830, "Tytsjerksteradiel": 16015, "Schiermonnikoog": 475, "Littenseradiel": 5380, "S\u00fadwest-Frysl\u00e2n": 41400, "Gaasterl\u00e2n-Sleat": 5035}, "Zuid-Holland": {"Korendijk": 5390, "Kaag en Braassem": 12685, "Capelle aan den IJssel": 34130, "Schoonhoven": 6005, "Alblasserdam": 10030, "Zoetermeer": 62805, "Wassenaar": 13520, "Waddinxveen": 12675, "Hendrik-Ido-Ambacht": 14565, "'s-Gravenhage": 256115, "Katwijk": 31560, "Gorinchem": 17845, "Binnenmaas": 14585, "Noordwijkerhout": 7810, "Alphen aan den Rijn": 36895, "Barendrecht": 24045, "Hillegom": 10555, "Westland": 51635, "Oud-Beijerland": 11960, "Rotterdam": 313035, "Leiden": 61570, "Zederik": 6795, "Midden-Delfland": 9030, "Giessenlanden": 7110, "Bodegraven-Reeuwijk": 16425, "Nederlek": 7160, "Voorschoten": 12745, "Bergambacht": 5045, "Cromstrijen": 6430, "Zoeterwoude": 4105, "Nieuwkoop": 13345, "Schiedam": 38770, "Zuidplas": 20540, "Lansingerland": 28380, "Maassluis": 16285, "Pijnacker-Nootdorp": 25305, "Dordrecht": 60080, "Albrandswaard": 12645, "Papendrecht": 16330, "Leerdam": 10550, "Lisse": 11345, "Boskoop": 7625, "Vlaardingen": 36290, "Leiderdorp": 13830, "Ridderkerk": 23435, "Delft": 46460, "Westvoorne": 7015, "Brielle": 8320, "Molenwaard": 14355, "Noordwijk": 12770, "Zwijndrecht": 22965, "Oegstgeest": 11975, "Rijswijk": 24975, "Goeree-Overflakkee": 24370, "Leidschendam-Voorburg": 37875, "Teylingen": 17955, "Sliedrecht": 12425, "Krimpen aan den IJssel": 14810, "Spijkenisse": 36965, "Hellevoetsluis": 19665, "Strijen": 4380, "Bernisse": 6185, "Hardinxveld-Giessendam": 8895, "Rijnwoude": 9240, "Gouda": 36200, "Ouderkerk": 4115, "Vlist": 4865}, "Drenthe": {"Hoogeveen": 27575, "Emmen": 54730, "De Wolden": 11845, "Aa en Hunze": 12855, "Noordenveld": 15625, "Coevorden": 17955, "Assen": 34195, "Midden-Drenthe": 16755, "Meppel": 16705, "Borger-Odoorn": 12825, "Tynaarlo": 16520, "Westerveld": 9570}, "Overijssel": {"Almelo": 36605, "Dalfsen": 13585, "Ommen": 8645, "Twenterand": 16745, "Hof van Twente": 17745, "Tubbergen": 10385, "Staphorst": 7935, "Dinkelland": 12820, "Oldenzaal": 16125, "Hengelo": 40625, "Zwolle": 62645, "Wierden": 11910, "Losser": 11225, "Haaksbergen": 12090, "Hellendoorn": 17870, "Steenwijkerland": 21700, "Hardenberg": 29430, "Enschede": 78175, "Kampen": 25625, "Olst-Wijhe": 8780, "Deventer": 50035, "Zwartewaterland": 10925, "Borne": 10920, "Rijssen-Holten": 18915, "Raalte": 18175}, "Noord-Brabant": {"Nuenen, Gerwen en Nederwetten": 11400, "Bladel": 9660, "Landerd": 7460, "Geldrop-Mierlo": 19560, "Steenbergen": 11655, "Boekel": 4920, "Gemert-Bakel": 14420, "Gilze en Rijen": 12840, "Alphen-Chaam": 4760, "Geertruidenberg": 10815, "Boxmeer": 14135, "Deurne": 15760, "Bergen op Zoom": 33540, "Heusden": 21645, "Someren": 9165, "Maasdonk": 5595, "Waalre": 8460, "Boxtel": 15340, "Reusel-De Mierden": 6205, "Laarbeek": 10745, "Waalwijk": 23330, "Heeze-Leende": 7640, "Bernheze": 14735, "Goirle": 11590, "Bergeijk": 8975, "Etten-Leur": 21365, "Asten": 7955, "Dongen": 12790, "Veldhoven": 22080, "Oisterwijk": 13080, "Roosendaal": 39070, "Sint-Oedenrode": 8980, "Woensdrecht": 10790, "Zundert": 10345, "'s-Hertogenbosch": 72540, "Grave": 6160, "Rucphen": 11135, "Eindhoven": 107100, "Sint-Michielsgestel": 13945, "Breda": 91110, "Eersel": 8970, "Haaren": 6595, "Sint Anthonis": 5700, "Valkenswaard": 15460, "Moerdijk": 18325, "Veghel": 18615, "Cuijk": 12390, "Drimmelen": 13350, "Schijndel": 11630, "Tilburg": 104845, "Helmond": 44345, "Woudrichem": 7210, "Oosterhout": 27230, "Mill en Sint Hubert": 5365, "Halderberge": 14735, "Loon op Zand": 11650, "Werkendam": 13250, "Cranendonck": 10070, "Son en Breugel": 8160, "Oirschot": 8840, "Aalburg": 6315, "Uden": 20650, "Hilvarenbeek": 7450, "Baarle-Nassau": 3290, "Vught": 12905, "Oss": 42480, "Best": 14285}, "Limburg": {"Simpelveld": 5505, "Roerdalen": 10495, "Voerendaal": 6325, "Roermond": 28670, "Mook en Middelaar": 3935, "Beek": 8415, "Nederweert": 8330, "Sittard-Geleen": 47735, "Nuth": 7820, "Horst aan de Maas": 20720, "Gulpen-Wittem": 7195, "Weert": 24280, "Heerlen": 44825, "Meerssen": 9810, "Vaals": 4935, "Kerkrade": 23665, "Onderbanken": 3960, "Schinnen": 6510, "Leudal": 17990, "Maasgouw": 11975, "Eijsden-Margraten": 12530, "Valkenburg aan de Geul": 8485, "Bergen (L.)": 6620, "Beesel": 6805, "Venlo": 50450, "Stein": 12805, "Venray": 21355, "Landgraaf": 19225, "Echt-Susteren": 16035, "Maastricht": 63255, "Brunssum": 14940, "Gennep": 8475, "Peel en Maas": 21325}, "Utrecht": {"Vianen": 9990, "Leusden": 14785, "Woudenberg": 6155, "Eemnes": 4425, "Bunschoten": 10135, "Woerden": 25435, "Wijk bij Duurstede": 11650, "Lopik": 6875, "De Bilt": 22040, "Nieuwegein": 30740, "Stichtse Vecht": 32400, "Rhenen": 9615, "Montfoort": 6780, "Baarn": 12600, "De Ronde Venen": 21545, "Zeist": 31740, "Houten": 24530, "Utrecht": 165690, "Oudewater": 5015, "Soest": 23315, "Utrechtse Heuvelrug": 24860, "Renswoude": 2450, "Veenendaal": 32075, "Bunnik": 7370, "Amersfoort": 76135, "IJsselstein": 17570}, "Zeeland": {"Sluis": 12165, "Veere": 10950, "Tholen": 12770, "Hulst": 13785, "Kapelle": 6280, "Borsele": 11220, "Noord-Beveland": 3750, "Goes": 18875, "Schouwen-Duiveland": 17200, "Vlissingen": 22320, "Terneuzen": 27510, "Reimerswaal": 10880, "Middelburg": 24480}}, "2012": {"Groningen": {"Oldambt": 19765, "Stadskanaal": 16705, "Eemsmond": 7980, "Menterwolde": 6060, "De Marne": 5125, "Marum": 5075, "Hoogezand-Sappemeer": 17615, "Winsum": 7030, "Bedum": 5225, "Haren": 9730, "Delfzijl": 13150, "Leek": 9805, "Grootegast": 5995, "Groningen": 97500, "Pekela": 6415, "Bellingwedde": 4640, "Slochteren": 7625, "Vlagtwedde": 8150, "Ten Boer": 3735, "Loppersum": 5080, "Appingedam": 6230, "Veendam": 14110, "Zuidhorn": 9375}, "Gelderland": {"Berkelland": 22290, "Neerijnen": 5930, "Oude IJsselstreek": 19945, "Renkum": 16355, "Buren": 12965, "Elburg": 11310, "Scherpenzeel": 4715, "Westervoort": 7720, "West Maas en Waal": 9195, "Brummen": 10810, "Ubbergen": 4765, "Neder-Betuwe": 11385, "Lingewaard": 23065, "Putten": 12025, "Lingewaal": 5455, "Winterswijk": 14560, "Heerde": 9245, "Rheden": 22395, "Rozendaal": 765, "Overbetuwe": 23275, "Lochem": 16945, "Culemborg": 13945, "Wageningen": 19285, "Hattem": 6020, "Harderwijk": 23055, "Duiven": 13010, "Doesburg": 5940, "Barneveld": 26905, "Nijkerk": 20155, "Voorst": 11875, "Arnhem": 75205, "Heumen": 8285, "Oldebroek": 11265, "Groesbeek": 9630, "Geldermalsen": 13280, "Apeldoorn": 79435, "Beuningen": 12745, "Doetinchem": 28400, "Zevenaar": 16465, "Epe": 16470, "Zaltbommel": 13375, "Druten": 9155, "Rijnwaarden": 5545, "Tiel": 20905, "Bronckhorst": 18845, "Ede": 55390, "Oost Gelre": 14710, "Zutphen": 24120, "Millingen aan de Rijn": 2950, "Ermelo": 13260, "Nunspeet": 13485, "Maasdriel": 11900, "Nijmegen": 86100, "Montferland": 17575, "Aalten": 13620, "Wijchen": 20640}, "Flevoland": {"Noordoostpolder": 22890, "Urk": 9360, "Lelystad": 37765, "Almere": 97290, "Dronten": 19945, "Zeewolde": 10490}, "Noord-Holland": {"Langedijk": 13525, "Muiden": 3340, "Haarlemmerliede en Spaarnwoude": 2775, "Zeevang": 3175, "Hilversum": 43950, "Velsen": 33995, "Wijdemeren": 11885, "Medemblik": 21200, "Castricum": 17620, "Hoorn": 36125, "Texel": 6895, "Naarden": 8905, "Zaanstad": 74970, "Aalsmeer": 15315, "Landsmeer": 5375, "Drechterland": 9505, "Bloemendaal": 11560, "Ouder-Amstel": 6780, "Zandvoort": 8650, "Heerhugowaard": 26025, "Opmeer": 5620, "Heemstede": 13890, "Harenkarspel": 7895, "Heemskerk": 20025, "Waterland": 8530, "Weesp": 9295, "Huizen": 21350, "Alkmaar": 47845, "Haarlemmermeer": 72390, "Schermer": 2680, "Heiloo": 11510, "Koggenland": 11110, "Den Helder": 28780, "Schagen": 9550, "Oostzaan": 4650, "Bergen (NH.)": 15810, "Amsterdam": 401105, "Uitgeest": 6425, "Edam-Volendam": 14330, "Diemen": 12890, "Bussum": 17115, "Purmerend": 40535, "Wormerland": 7890, "Beverwijk": 20125, "Zijpe": 5740, "Amstelveen": 43650, "Blaricum": 4670, "Graft-De Rijp": 3205, "Enkhuizen": 9140, "Laren": 5940, "Stede Broec": 10610, "Uithoorn": 14335, "Hollands Kroon": 23555, "Beemster": 4360, "Haarlem": 77895}, "Friesland": {"Skarsterl\u00e2n": 13725, "Leeuwarderadeel": 5125, "Ooststellingwerf": 12920, "Ameland": 1775, "Harlingen": 7885, "Smallingerland": 27885, "Franekeradeel": 10210, "Weststellingwerf": 12860, "Terschelling": 2235, "Dantumadiel": 9620, "Achtkarspelen": 13830, "Opsterland": 15005, "Dongeradeel": 12095, "Boarnsterhim": 9660, "Kollumerland en Nieuwkruisland": 6275, "het Bildt": 5260, "Ferwerderadiel": 4305, "Heerenveen": 22115, "Lemsterland": 6660, "Menameradiel": 6765, "Vlieland": 550, "Leeuwarden": 48595, "Tytsjerksteradiel": 16125, "Schiermonnikoog": 470, "Littenseradiel": 5380, "S\u00fadwest-Frysl\u00e2n": 41345, "Gaasterl\u00e2n-Sleat": 5045}, "Zuid-Holland": {"Korendijk": 5400, "Kaag en Braassem": 12675, "Capelle aan den IJssel": 34200, "Graafstroom": 4785, "Schoonhoven": 5985, "Alblasserdam": 9970, "Zoetermeer": 62375, "Wassenaar": 13565, "Waddinxveen": 12680, "Hendrik-Ido-Ambacht": 14410, "'s-Gravenhage": 254190, "Katwijk": 31460, "Gorinchem": 17835, "Middelharnis": 9195, "Binnenmaas": 14630, "Noordwijkerhout": 7760, "Nieuw-Lekkerland": 4635, "Alphen aan den Rijn": 36895, "Barendrecht": 23825, "Hillegom": 10525, "Westland": 51180, "Oud-Beijerland": 11910, "Rotterdam": 312490, "Leiden": 60900, "Zederik": 6755, "Midden-Delfland": 8990, "Giessenlanden": 7130, "Bodegraven-Reeuwijk": 16395, "Nederlek": 7100, "Voorschoten": 12580, "Bergambacht": 5020, "Cromstrijen": 6435, "Leidschendam-Voorburg": 37785, "Zoeterwoude": 4130, "Nieuwkoop": 13325, "Schiedam": 38750, "Zuidplas": 20495, "Zwijndrecht": 22855, "Maassluis": 16245, "Pijnacker-Nootdorp": 25080, "Dordrecht": 60310, "Albrandswaard": 12615, "Papendrecht": 16285, "Leerdam": 10510, "Liesveld": 4870, "Lisse": 11425, "Boskoop": 7560, "Vlaardingen": 36330, "Leiderdorp": 13825, "Ridderkerk": 23340, "Delft": 46375, "Westvoorne": 7000, "Brielle": 8160, "Noordwijk": 12680, "Oostflakkee": 5205, "Oegstgeest": 11840, "Rijswijk": 24810, "Lansingerland": 27740, "Ouderkerk": 4075, "Goedereede": 5755, "Sliedrecht": 12335, "Krimpen aan den IJssel": 14740, "Spijkenisse": 36805, "Teylingen": 17890, "Hellevoetsluis": 19725, "Strijen": 4430, "Bernisse": 6180, "Hardinxveld-Giessendam": 8885, "Rijnwoude": 9250, "Gouda": 36380, "Dirksland": 4240, "Vlist": 4910}, "Drenthe": {"Hoogeveen": 27610, "Emmen": 54925, "De Wolden": 11855, "Aa en Hunze": 12905, "Noordenveld": 15615, "Coevorden": 17965, "Assen": 34275, "Midden-Drenthe": 16820, "Meppel": 16655, "Borger-Odoorn": 12965, "Tynaarlo": 16445, "Westerveld": 9645}, "Overijssel": {"Almelo": 36670, "Dalfsen": 13500, "Ommen": 8680, "Twenterand": 16735, "Hof van Twente": 17925, "Tubbergen": 10425, "Staphorst": 7900, "Dinkelland": 12825, "Oldenzaal": 16100, "Hengelo": 40650, "Zwolle": 62245, "Wierden": 11895, "Losser": 11280, "Haaksbergen": 12130, "Hellendoorn": 17910, "Steenwijkerland": 21695, "Hardenberg": 29325, "Enschede": 77825, "Kampen": 25500, "Olst-Wijhe": 8735, "Deventer": 50120, "Zwartewaterland": 10870, "Borne": 10785, "Rijssen-Holten": 18895, "Raalte": 18275}, "Noord-Brabant": {"Nuenen, Gerwen en Nederwetten": 11365, "Bladel": 9615, "Landerd": 7365, "Geldrop-Mierlo": 19550, "Steenbergen": 11610, "Boekel": 4870, "Gemert-Bakel": 14385, "Gilze en Rijen": 12705, "Alphen-Chaam": 4700, "Geertruidenberg": 10795, "Boxmeer": 14205, "Deurne": 15760, "Bergen op Zoom": 33470, "Heusden": 21560, "Someren": 9125, "Maasdonk": 5615, "Waalre": 8360, "Boxtel": 15295, "Reusel-De Mierden": 6195, "Laarbeek": 10685, "Waalwijk": 23315, "Heeze-Leende": 7600, "Bernheze": 14780, "Goirle": 11490, "Bergeijk": 8935, "Etten-Leur": 21245, "Asten": 7995, "Dongen": 12705, "Veldhoven": 22000, "Oisterwijk": 13075, "Roosendaal": 39180, "Sint-Oedenrode": 8960, "Woensdrecht": 10815, "Zundert": 10355, "'s-Hertogenbosch": 72085, "Grave": 6190, "Rucphen": 11150, "Eindhoven": 106480, "Sint-Michielsgestel": 13985, "Breda": 90425, "Eersel": 8945, "Haaren": 6665, "Sint Anthonis": 5740, "Valkenswaard": 15515, "Moerdijk": 18325, "Veghel": 18675, "Cuijk": 12320, "Drimmelen": 13330, "Schijndel": 11490, "Tilburg": 104565, "Helmond": 44235, "Woudrichem": 7205, "Oosterhout": 27400, "Mill en Sint Hubert": 5385, "Halderberge": 14760, "Loon op Zand": 11645, "Werkendam": 13235, "Cranendonck": 10095, "Son en Breugel": 8005, "Oirschot": 8810, "Aalburg": 6310, "Uden": 20560, "Hilvarenbeek": 7445, "Baarle-Nassau": 3300, "Vught": 13060, "Oss": 42360, "Best": 14340}, "Limburg": {"Simpelveld": 5485, "Roerdalen": 10530, "Voerendaal": 6350, "Roermond": 28420, "Mook en Middelaar": 3950, "Beek": 8460, "Nederweert": 8330, "Sittard-Geleen": 48030, "Nuth": 7930, "Horst aan de Maas": 20800, "Gulpen-Wittem": 7205, "Weert": 24325, "Heerlen": 45015, "Meerssen": 9875, "Vaals": 4945, "Kerkrade": 23740, "Onderbanken": 4015, "Schinnen": 6560, "Leudal": 18020, "Maasgouw": 12060, "Eijsden-Margraten": 12495, "Valkenburg aan de Geul": 8570, "Bergen (L.)": 6630, "Beesel": 6820, "Venlo": 50430, "Stein": 12885, "Venray": 21330, "Landgraaf": 19335, "Echt-Susteren": 16070, "Maastricht": 62820, "Brunssum": 14965, "Gennep": 8500, "Peel en Maas": 21300}, "Utrecht": {"Vianen": 9990, "Leusden": 14750, "Woudenberg": 6010, "Eemnes": 4460, "Bunschoten": 10080, "Woerden": 25320, "Wijk bij Duurstede": 11670, "Lopik": 6895, "De Bilt": 22100, "Nieuwegein": 30660, "Stichtse Vecht": 32290, "Rhenen": 9625, "Montfoort": 6790, "Baarn": 12645, "De Ronde Venen": 21620, "Zeist": 31725, "Houten": 24395, "Utrecht": 162995, "Oudewater": 5000, "Soest": 23405, "Utrechtse Heuvelrug": 24965, "Renswoude": 2425, "Veenendaal": 32015, "Bunnik": 7310, "Amersfoort": 75400, "IJsselstein": 17550}, "Zeeland": {"Sluis": 12165, "Veere": 10965, "Tholen": 12745, "Hulst": 13850, "Kapelle": 6230, "Borsele": 11185, "Noord-Beveland": 3755, "Goes": 18875, "Schouwen-Duiveland": 17285, "Vlissingen": 22350, "Terneuzen": 27490, "Reimerswaal": 10800, "Middelburg": 24525}}}