{"2014": {"Bladel": "263", "Westervoort": "2158", "Assen": "821", "Capelle aan den IJssel": "4655", "Waalre": "749", "Twenterand": "319", "Noordenveld": "155", "Noordoostpolder": "101", "Winsum": "137", "Duiven": "755", "Nijkerk": "585", "Voorst": "193", "Oldebroek": "234", "Schermer": "90", "Almere": "1516", "Berkelland": "173", "Bronckhorst": "130", "Echt-Susteren": "310", "Bergen op Zoom": "827", "Strijen": "172", "Littenseradiel": "84", "Vlaardingen": "3002", "Deventer": "749", "Molenwaard": "245", "Veendam": "366", "Wijchen": "619", "De Friese Meren": "146", "Elburg": "355", "Rheden": "534", "Zuidplas": "685", "Coevorden": "121", "Lelystad": "329", "Weststellingwerf": "115", "Nieuwkoop": "344", "'s-Hertogenbosch": "1703", "Eindhoven": "2520", "Hengelo": "1330", "Beverwijk": "2189", "Haaksbergen": "232", "Beuningen": "579", "Utrecht": "3481", "Bellingwedde": "82", "Edam-Volendam": "1775", "Laren": "875", "Soest": "984", "Venray": "264", "Leidschendam-Voorburg": "2245", "Woerden": "566", "Uden": "610", "Beemster": "126", "Tilburg": "1794", "Vught": "765", "Buren": "194", "Boekel": "292", "Leusden": "495", "Dalfsen": "168", "Renkum": "687", "Leek": "310", "Kerkrade": "2136", "Giessenlanden": "227", "Schiedam": "4247", "Winterswijk": "209", "Cromstrijen": "234", "Tynaarlo": "227", "Sint Anthonis": "118", "Ridderkerk": "1909", "Bussum": "4036", "Roosendaal": "723", "Druten": "483", "Tytsjerksteradiel": "214", "Blaricum": "815", "Maastricht": "2163", "Maasdriel": "365", "Amersfoort": "2402", "Zundert": "177", "Rijssen-Holten": "400", "Simpelveld": "677", "Zeevang": "167", "Lansingerland": "1053", "Scherpenzeel": "689", "Zoetermeer": "3578", "Velsen": "1501", "Wijdemeren": "484", "Lingewaal": "219", "Harlingen": "634", "Lopik": "185", "Montferland": "331", "Sint-Oedenrode": "278", "Huizen": "2609", "Stichtse Vecht": "661", "Zwolle": "1106", "Eersel": "220", "Urk": "1692", "Pekela": "259", "Brielle": "591", "Terschelling": "57", "Tholen": "173", "Ede": "348", "Veenendaal": "3243", "Vlagtwedde": "95", "Landgraaf": "1528", "Vlist": "180", "Eemsmond": "84", "Schouwen-Duiveland": "147", "Teylingen": "1252", "Eemnes": "283", "Putten": "280", "Katwijk": "2558", "Heerde": "235", "Son en Breugel": "626", "Stein": "1205", "De Bilt": "634", "Nieuwegein": "2582", "Ouder-Amstel": "550", "Doesburg": "989", "Dongeradeel": "145", "Baarn": "748", "Kaag en Braassem": "407", "Alkmaar": "3240", "Zeist": "1263", "Schagen": "274", "Helmond": "1677", "Slochteren": "103", "Ermelo": "304", "Naarden": "803", "Cranendonck": "266", "Nijmegen": "3139", "Loppersum": "92", "Zwartewaterland": "268", "Borne": "842", "Roermond": "935", "Schoonhoven": "1896", "Nederweert": "168", "Heusden": "547", "Marum": "161", "Albrandswaard": "1150", "Westland": "1298", "Culemborg": "938", "Leiden": "5524", "Onderbanken": "372", "Zandvoort": "517", "Bergambacht": "284", "Grave": "467", "Arnhem": "1540", "Noordwijkerhout": "706", "Breda": "1425", "Heiloo": "1210", "Millingen aan de Rijn": "680", "Vlissingen": "1300", "Venlo": "806", "Dantumadiel": "223", "Lochem": "156", "Emmen": "322", "Kapelle": "337", "Oisterwijk": "404", "Borger-Odoorn": "93", "Rijswijk": "3390", "Voerendaal": "395", "Mook en Middelaar": "448", "Ooststellingwerf": "115", "Neder-Betuwe": "376", "Goes": "399", "'s-Gravenhage": "6216", "Bunschoten": "673", "Gorinchem": "1867", "Texel": "84", "Waalwijk": "720", "Heeze-Leende": "148", "Tiel": "1268", "Oud-Beijerland": "1266", "Goirle": "549", "Diemen": "2163", "Schinnen": "536", "Hoorn": "3530", "Franekeradeel": "199", "Halderberge": "394", "Zeewolde": "87", "Vlieland": "31", "Wormerland": "408", "Spijkenisse": "2780", "Hellevoetsluis": "1235", "Zuidhorn": "150", "Langedijk": "1123", "Midden-Delfland": "390", "Ommen": "96", "Borsele": "159", "Someren": "233", "Boxtel": "476", "Zaanstad": "2037", "Hof van Twente": "165", "Zederik": "185", "Opsterland": "133", "Dinkelland": "148", "Waterland": "329", "Oldambt": "170", "Oldenzaal": "1491", "Valkenburg aan de Geul": "454", "Dordrecht": "1506", "Wierden": "252", "Leerdam": "609", "Bergen (NH.)": "310", "Delft": "4381", "Purmerend": "3427", "Sittard-Geleen": "1186", "Krimpen aan den IJssel": "3754", "Bernisse": "216", "Amsterdam": "4888", "Neerijnen": "182", "Gilze en Rijen": "398", "Brummen": "252", "Medemblik": "357", "Bedum": "236", "Dongen": "866", "Vaals": "406", "Veldhoven": "1392", "Harderwijk": "1183", "Dronten": "121", "Oudewater": "253", "Eijsden-Margraten": "323", "Sint-Michielsgestel": "481", "Nederlek": "507", "Hellendoorn": "259", "Gulpen-Wittem": "198", "Veghel": "479", "Westerveld": "68", "Zevenaar": "606", "Hilversum": "1894", "Zoeterwoude": "380", "S\u00fadwest-Frysl\u00e2n": "185", "Gennep": "363", "Roerdalen": "236", "Woudenberg": "340", "Wassenaar": "504", "Deurne": "271", "Ameland": "61", "Hattem": "509", "Maasgouw": "523", "Barneveld": "308", "Weesp": "886", "Alphen aan den Rijn": "844", "Kollumerland en Nieuwkruisland": "117", "Aa en Hunze": "92", "Ferwerderadiel": "90", "Uitgeest": "691", "Zaltbommel": "341", "Menameradiel": "199", "Woudrichem": "293", "Veere": "164", "Castricum": "693", "Goeree-Overflakkee": "185", "Schiermonnikoog": "25", "Zwijndrecht": "2190", "Nuenen, Gerwen en Nederwetten": "671", "Oude IJsselstreek": "290", "Steenbergen": "159", "Schijndel": "562", "Ubbergen": "280", "Horst aan de Maas": "221", "Sluis": "85", "Drechterland": "326", "Voorschoten": "2237", "Opmeer": "274", "Rhenen": "454", "Groningen": "2534", "Etten-Leur": "765", "Maasdonk": "302", "Hoogeveen": "429", "Haaren": "235", "Apeldoorn": "464", "Den Helder": "1255", "Westvoorne": "262", "Oegstgeest": "3139", "Smallingerland": "471", "Oosterhout": "751", "Hulst": "136", "Drimmelen": "278", "Montfoort": "362", "Aalburg": "255", "Uithoorn": "1558", "Hardinxveld-Giessendam": "1049", "Heerenveen": "262", "Haarlemmerliede en Spaarnwoude": "287", "Hoogezand-Sappemeer": "515", "Midden-Drenthe": "98", "Lingewaard": "736", "Laarbeek": "394", "Pijnacker-Nootdorp": "1367", "Rozendaal": "54", "Rucphen": "344", "Geertruidenberg": "810", "Maassluis": "3778", "Geldermalsen": "263", "Rijnwaarden": "275", "Oost Gelre": "271", "Sliedrecht": "1911", "Enkhuizen": "1449", "Brunssum": "1683", "Papendrecht": "3416", "Appingedam": "507", "Terneuzen": "218", "Almelo": "1077", "Muiden": "435", "Vianen": "499", "Menterwolde": "153", "Hendrik-Ido-Ambacht": "2726", "Nuth": "471", "Binnenmaas": "414", "Haren": "413", "Delfzijl": "193", "Heerhugowaard": "1391", "Heemskerk": "1437", "Koggenland": "280", "Steenwijkerland": "150", "Leiderdorp": "2321", "Moerdijk": "230", "Cuijk": "484", "Noordwijk": "724", "Nunspeet": "207", "Leeuwarden": "695", "Zutphen": "1151", "Kampen": "359", "Stede Broec": "1477", "Weert": "466", "De Wolden": "105", "Beek": "774", "Leeuwarderadeel": "251", "Alphen-Chaam": "104", "Renswoude": "267", "Stadskanaal": "279", "Reusel-De Mierden": "163", "IJsselstein": "1624", "Barendrecht": "2380", "Hillegom": "1623", "Wageningen": "1228", "Tubbergen": "144", "Asten": "234", "Leudal": "222", "De Ronde Venen": "425", "Bergeijk": "181", "Heemstede": "2861", "Middelburg": "982", "Epe": "207", "Mill en Sint Hubert": "208", "Oss": "558", "Werkendam": "253", "Bernheze": "331", "Houten": "878", "Achtkarspelen": "274", "Bunnik": "395", "Hollands Kroon": "133", "Hilvarenbeek": "159", "Best": "834", "Peel en Maas": "272", "Geldrop-Mierlo": "1253", "Gemert-Bakel": "240", "Waddinxveen": "912", "Meppel": "592", "De Marne": "60", "Rotterdam": "2960", "Wijk bij Duurstede": "485", "Aalsmeer": "1508", "Meerssen": "712", "Bodegraven-Reeuwijk": "435", "Staphorst": "122", "Woensdrecht": "236", "Groesbeek": "430", "Losser": "229", "Lisse": "1423", "het Bildt": "115", "Boxmeer": "252", "Landsmeer": "463", "Enschede": "1125", "Doetinchem": "713", "Noord-Beveland": "88", "Graft-De Rijp": "324", "Grootegast": "140", "Gouda": "4212", "Haarlem": "5309", "Raalte": "213", "Korendijk": "140", "Alblasserdam": "2257", "West Maas en Waal": "238", "Reimerswaal": "215", "Utrechtse Heuvelrug": "363", "Olst-Wijhe": "156", "Bloemendaal": "555", "Haarlemmermeer": "806", "Heumen": "410", "Overbetuwe": "427", "Bergen (L.)": "128", "Beesel": "484", "Valkenswaard": "552", "Oostzaan": "792", "Aalten": "280", "Hardenberg": "191", "Heerlen": "1963", "Amstelveen": "2052", "Loon op Zand": "460", "Oirschot": "177", "Ten Boer": "165", "Landerd": "217", "Baarle-Nassau": "87", "Ouderkerk": "303"}}